Workbook

Sheet POA2026_ej
A1: Resultado_cod | B1: Resultado | C1: Producto_cod | D1: Producto | E1: Tipo_producto_cod | F1: Tipo de producto | G1: Nivel | H1: Entidad_p6 | I1: Actividad_cod | J1: Actividad_name | K1: Actividad | L1: Indicador | M1: Unidad de medida | N1: Medio de verificación | O1: Logro Esperado | P1: ene_pl | Q1: feb_pl | R1: mar_pl | S1: abr_pl | T1: may_pl | U1: jun_pl | V1: jul_pl | W1: ago_pl | X1: set_pl | Y1: oct_pl | Z1: nov_pl | AA1: dic_pl | AB1: Pl_total | AC1: ene_ej | AD1: feb_ej | AE1: mar_ej | AF1: abr_ej | AG1: may_ej | AH1: jun_ej | AI1: jul_ej | AJ1: ago_ej | AK1: set_ej | AL1: oct_ej | AM1: nov_ej | AN1: dic_ej | AO1: Ej_total
A2: D1 | B2: =IFERROR(CONCATENATE(A2,". ",VLOOKUP(A2,'results, prods y acts'!$A$2:$B$8,2,FALSE)),"") -> D1. Los procesos estratégicos y de soporte se realizan de forma eficaz y eficiente | C2: D1.1 | D2: =IFERROR(CONCATENATE(C2,". ",VLOOKUP(C2,'results, prods y acts'!$D$2:$E$12,2,FALSE)),CONCATENATE(C2,". ")) -> D1.1. Informes semestrales | I2: D1.1.1 | J2: Envío a SECO | K2: =CONCATENATE(I2,". ",J2) -> D1.1.1. Envío a SECO | L2: Número de informes | M2: Informe | N2: Correo de envío | O2: Informes enviados en el tiempo esperado | Q2: 1 | W2: 1 | AB2: =SUM(P2:AA2) -> 2
A3: D1 | B3: =IFERROR(CONCATENATE(A3,". ",VLOOKUP(A3,'results, prods y acts'!$A$2:$B$8,2,FALSE)),"") -> D1. Los procesos estratégicos y de soporte se realizan de forma eficaz y eficiente | C3: D1.1 | D3: =IFERROR(CONCATENATE(C3,". ",VLOOKUP(C3,'results, prods y acts'!$D$2:$E$12,2,FALSE)),CONCATENATE(C3,". ")) -> D1.1. Informes semestrales | I3: D1.1.2 | J3: Absolución de comentarios | K3: =CONCATENATE(I3,". ",J3) -> D1.1.2. Absolución de comentarios | L3: Número de respuestas | M3: Informe | N3: Correo de envío | O3: Informes enviados en el tiempo esperado | Q3: 1 | W3: 1 | AB3: =SUM(P3:AA3) -> 2
A4: D1 | B4: =IFERROR(CONCATENATE(A4,". ",VLOOKUP(A4,'results, prods y acts'!$A$2:$B$8,2,FALSE)),"") -> D1. Los procesos estratégicos y de soporte se realizan de forma eficaz y eficiente | C4: D1.2 | D4: =IFERROR(CONCATENATE(C4,". ",VLOOKUP(C4,'results, prods y acts'!$D$2:$E$12,2,FALSE)),CONCATENATE(C4,". ")) -> D1.2. Planificación Operativa | I4: D1.2.1 | J4: Reuniones de trabajo con el equipo del Programa para el diseño y aprobación del POA | K4: =CONCATENATE(I4,". ",J4) -> D1.2.1. Reuniones de trabajo con el equipo del Programa para el diseño y aprobación del POA | L4: Número de planes | M4: Plan | N4: Correo de envío | O4: Plan aprobado | AA4: 1 | AB4: =SUM(P4:AA4) -> 1
A5: D1 | B5: =IFERROR(CONCATENATE(A5,". ",VLOOKUP(A5,'results, prods y acts'!$A$2:$B$8,2,FALSE)),"") -> D1. Los procesos estratégicos y de soporte se realizan de forma eficaz y eficiente | C5: D1.3 | D5: =IFERROR(CONCATENATE(C5,". ",VLOOKUP(C5,'results, prods y acts'!$D$2:$E$12,2,FALSE)),CONCATENATE(C5,". ")) -> D1.3. Monitoreo y Evaluación | I5: D1.3.1 | J5: Reuniones mensuales de seguimiento | K5: =CONCATENATE(I5,". ",J5) -> D1.3.1. Reuniones mensuales de seguimiento | L5: Número de reuniones | M5: Reuniones | N5: Acta de reunión | O5: Las áreas encuentran puntos de mejora para el desarrollo de estrategias para la consecución de sus objetivos. | P5: 1 | Q5: 1 | R5: 1 | S5: 1 | T5: 1 | U5: 1 | V5: 1 | W5: 1 | X5: 1 | Y5: 1 | Z5: 1 | AA5: 1 | AB5: =SUM(P5:AA5) -> 12
A6: D1 | B6: =IFERROR(CONCATENATE(A6,". ",VLOOKUP(A6,'results, prods y acts'!$A$2:$B$8,2,FALSE)),"") -> D1. Los procesos estratégicos y de soporte se realizan de forma eficaz y eficiente | C6: D1.3 | D6: =IFERROR(CONCATENATE(C6,". ",VLOOKUP(C6,'results, prods y acts'!$D$2:$E$12,2,FALSE)),CONCATENATE(C6,". ")) -> D1.3. Monitoreo y Evaluación | I6: D1.3.2 | J6: Reuniones de identificación y gestión de riesgos | K6: =CONCATENATE(I6,". ",J6) -> D1.3.2. Reuniones de identificación y gestión de riesgos | L6: Número de reuniones | M6: Reuniones | N6: Acta de reunión | O6: Se analizan posibles riesgos y, de requerirse, se establecen medidas para su mitigación | Q6: 1 | W6: 1 | AB6: =SUM(P6:AA6) -> 2
A7: D1 | B7: =IFERROR(CONCATENATE(A7,". ",VLOOKUP(A7,'results, prods y acts'!$A$2:$B$8,2,FALSE)),"") -> D1. Los procesos estratégicos y de soporte se realizan de forma eficaz y eficiente | C7: D1.4 | D7: =IFERROR(CONCATENATE(C7,". ",VLOOKUP(C7,'results, prods y acts'!$D$2:$E$12,2,FALSE)),CONCATENATE(C7,". ")) -> D1.4. Coordinación con socios, cooperantes y Programas de SECO | I7: D1.4.1 | J7: Espacios de incidencia política | K7: =CONCATENATE(I7,". ",J7) -> D1.4.1. Espacios de incidencia política | L7: Número de reuniones | M7: Reuniones | N7: Acta de reunión | O7: Se recogen retroalimentación del MEF | U7: 1 | AA7: 1 | AB7: =SUM(P7:AA7) -> 2
A8: D1 | B8: =IFERROR(CONCATENATE(A8,". ",VLOOKUP(A8,'results, prods y acts'!$A$2:$B$8,2,FALSE)),"") -> D1. Los procesos estratégicos y de soporte se realizan de forma eficaz y eficiente | C8: D1.4 | D8: =IFERROR(CONCATENATE(C8,". ",VLOOKUP(C8,'results, prods y acts'!$D$2:$E$12,2,FALSE)),CONCATENATE(C8,". ")) -> D1.4. Coordinación con socios, cooperantes y Programas de SECO | I8: D1.4.2 | J8: Reuniones del Comité de Piloteo con SECO y Basel Institute sede Suiza | K8: =CONCATENATE(I8,". ",J8) -> D1.4.2. Reuniones del Comité de Piloteo con SECO y Basel Institute sede Suiza | L8: Número de reuniones | M8: Reuniones | N8: Acta de reunión | O8: Se recoge retroalimentación para la implementación del Programa | V8: 1 | Y8: 1 | AB8: =SUM(P8:AA8) -> 2
A9: D1 | B9: =IFERROR(CONCATENATE(A9,". ",VLOOKUP(A9,'results, prods y acts'!$A$2:$B$8,2,FALSE)),"") -> D1. Los procesos estratégicos y de soporte se realizan de forma eficaz y eficiente | C9: D1.4 | D9: =IFERROR(CONCATENATE(C9,". ",VLOOKUP(C9,'results, prods y acts'!$D$2:$E$12,2,FALSE)),CONCATENATE(C9,". ")) -> D1.4. Coordinación con socios, cooperantes y Programas de SECO | I9: D1.4.3 | J9: Difusión de Asistencias Técnicas R1,R2,R3,R4, R5 | K9: =CONCATENATE(I9,". ",J9) -> D1.4.3. Difusión de Asistencias Técnicas R1,R2,R3,R4, R5 | L9: Número de herramientas o eventos de difusión elaborados en el mes sobre Asistencias Técnicas realizadas. | M9: Informe | N9: Documento | O9: Se difunden avances de resultados del Programa y se cumplen al 100% los resultados previstos por la Dirección (Buenos resultados en entrevistas con Autoridades, en ratificación de Planes de acción y en Interaacción con otros Programas de SECO) | P9: 1 | Q9: 1 | R9: 1 | S9: 1 | T9: 1 | U9: 1 | V9: 1 | W9: 1 | X9: 1 | Y9: 1 | Z9: 1 | AA9: 1 | AB9: =SUM(P9:AA9) -> 12
A10: D1 | B10: =IFERROR(CONCATENATE(A10,". ",VLOOKUP(A10,'results, prods y acts'!$A$2:$B$8,2,FALSE)),"") -> D1. Los procesos estratégicos y de soporte se realizan de forma eficaz y eficiente | C10: D1.4 | D10: =IFERROR(CONCATENATE(C10,". ",VLOOKUP(C10,'results, prods y acts'!$D$2:$E$12,2,FALSE)),CONCATENATE(C10,". ")) -> D1.4. Coordinación con socios, cooperantes y Programas de SECO | I10: D1.4.4 | J10: Difusión de Capacitaciones/Fortalecimiento de Capacidades realizados por R1, R2,R3,R4,R5 | K10: =CONCATENATE(I10,". ",J10) -> D1.4.4. Difusión de Capacitaciones/Fortalecimiento de Capacidades realizados por R1, R2,R3,R4,R5 | L10: Número de herramientas o eventos de difusión elaboradas/ desarrolladas en el mes sobre Capacitaciones/ Fortalecimiento de Capacidades realizadas | M10: Informe | N10: Documento | O10: Se difunden avances de resultados del Programa y se cumplen al 100% los resultados previstos por la Dirección (Buenos resultados en entrevistas con Autoridades, en ratificación de Planes de acción y en Interaacción con Programas de SECO) | S10: 1 | V10: 1 | W10: 1 | AB10: =SUM(P10:AA10) -> 3
A11: D1 | B11: =IFERROR(CONCATENATE(A11,". ",VLOOKUP(A11,'results, prods y acts'!$A$2:$B$8,2,FALSE)),"") -> D1. Los procesos estratégicos y de soporte se realizan de forma eficaz y eficiente | C11: D1.4 | D11: =IFERROR(CONCATENATE(C11,". ",VLOOKUP(C11,'results, prods y acts'!$D$2:$E$12,2,FALSE)),CONCATENATE(C11,". ")) -> D1.4. Coordinación con socios, cooperantes y Programas de SECO | I11: D1.4.5 | J11: Difusión de Instrumentos de Mejora de la Gestión realizados por el Programa (R1,R2,R3,R4,R5) | K11: =CONCATENATE(I11,". ",J11) -> D1.4.5. Difusión de Instrumentos de Mejora de la Gestión realizados por el Programa (R1,R2,R3,R4,R5) | L11: Número de herramientas o eventos de difusión elaboradas/ desarrolladas en el mes sobre Capacitaciones/ Fortalecimiento de Capacidades realizadas | M11: Informe | N11: Documento | O11: Se difunden avances de resultados del Programa y se cumplen al 100% los resultados previstos por la Dirección (Buenos resultados en entrevistas con Autoridades, en ratificación de Planes de acción y en Interaacción con otros Programas de SECO) | V11: 1 | AB11: =SUM(P11:AA11) -> 1
A12: D1 | B12: =IFERROR(CONCATENATE(A12,". ",VLOOKUP(A12,'results, prods y acts'!$A$2:$B$8,2,FALSE)),"") -> D1. Los procesos estratégicos y de soporte se realizan de forma eficaz y eficiente | C12: D1.4 | D12: =IFERROR(CONCATENATE(C12,". ",VLOOKUP(C12,'results, prods y acts'!$D$2:$E$12,2,FALSE)),CONCATENATE(C12,". ")) -> D1.4. Coordinación con socios, cooperantes y Programas de SECO | I12: D1.4.7 | J12: Visitas técnicas a los GSN (GR y MP) | K12: =CONCATENATE(I12,". ",J12) -> D1.4.7. Visitas técnicas a los GSN (GR y MP) | L12: Número de visitas técnicas | M12: Reunión | N12: Reporte | O12: Las autoridades de los GSN se preparan para el cierre de gestión 2023-2026 | P12: 1 | Q12: 1 | R12: 1 | S12: 1 | T12: 1 | U12: 1 | V12: 1 | W12: 1 | X12: 1 | Y12: 1 | Z12: 1 | AA12: 1 | AB12: =SUM(P12:AA12) -> 12
A13: D1 | B13: =IFERROR(CONCATENATE(A13,". ",VLOOKUP(A13,'results, prods y acts'!$A$2:$B$8,2,FALSE)),"") -> D1. Los procesos estratégicos y de soporte se realizan de forma eficaz y eficiente | C13: D1.4 | D13: =IFERROR(CONCATENATE(C13,". ",VLOOKUP(C13,'results, prods y acts'!$D$2:$E$12,2,FALSE)),CONCATENATE(C13,". ")) -> D1.4. Coordinación con socios, cooperantes y Programas de SECO | I13: D1.4.6 | J13: Reuniones de coordinación con gerentes clave (Planeamiento y Presupuesto) de los GR | K13: =CONCATENATE(I13,". ",J13) -> D1.4.6. Reuniones de coordinación con gerentes clave (Planeamiento y Presupuesto) de los GR | L13: Número de reuniones de coordinación con autoridades de los GR | M13: Reunión | N13: Reporte | O13: Se brinda acompañamiento técnico a las autoridades de los GSN en el proceso de transición hacia el nuevo periodo de gobierno, en el contexto de las elecciones generales 2026 | P13: 1 | Q13: 1 | R13: 1 | S13: 1 | T13: 1 | U13: 1 | AB13: =SUM(P13:AA13) -> 6
A14: D1 | B14: =IFERROR(CONCATENATE(A14,". ",VLOOKUP(A14,'results, prods y acts'!$A$2:$B$8,2,FALSE)),"") -> D1. Los procesos estratégicos y de soporte se realizan de forma eficaz y eficiente | C14: D1.4 | D14: =IFERROR(CONCATENATE(C14,". ",VLOOKUP(C14,'results, prods y acts'!$D$2:$E$12,2,FALSE)),CONCATENATE(C14,". ")) -> D1.4. Coordinación con socios, cooperantes y Programas de SECO | I14: D1.4.8 | J14: Reuniones estratégicas con candidatos a autoridades subnacionales | K14: =CONCATENATE(I14,". ",J14) -> D1.4.8. Reuniones estratégicas con candidatos a autoridades subnacionales | L14: Número de reuniones de presentación y coordinacion con candidatos a autoridades de los GSN | M14: Reunión | N14: Reporte | O14: Articulación temprana con candidatos a Gobernadores Regionales y Alcaldes Provinciales para asegurar continuidad técnica | W14: 1 | X14: 1 | Y14: 1 | Z14: 1 | AA14: 1 | AB14: =SUM(P14:AA14) -> 5
A15: D1 | B15: =IFERROR(CONCATENATE(A15,". ",VLOOKUP(A15,'results, prods y acts'!$A$2:$B$8,2,FALSE)),"") -> D1. Los procesos estratégicos y de soporte se realizan de forma eficaz y eficiente | C15: D1.5 | D15: =IFERROR(CONCATENATE(C15,". ",VLOOKUP(C15,'results, prods y acts'!$D$2:$E$12,2,FALSE)),CONCATENATE(C15,". ")) -> D1.5. Evaluación de los GSN | I15: D1.5.1 | J15: Diseño de la metodología de evaluación de las finanzas públicas en GSN | K15: =CONCATENATE(I15,". ",J15) -> D1.5.1. Diseño de la metodología de evaluación de las finanzas públicas en GSN | L15: Número de documento | M15: Documento | N15: Informe | O15: Se define una metodología ad hoc para la evaluación de la gestión de las finanzas públicas en GSN | T15: 1 | AB15: =SUM(P15:AA15) -> 1
A16: D1 | B16: =IFERROR(CONCATENATE(A16,". ",VLOOKUP(A16,'results, prods y acts'!$A$2:$B$8,2,FALSE)),"") -> D1. Los procesos estratégicos y de soporte se realizan de forma eficaz y eficiente | C16: D1.6 | D16: =IFERROR(CONCATENATE(C16,". ",VLOOKUP(C16,'results, prods y acts'!$D$2:$E$12,2,FALSE)),CONCATENATE(C16,". ")) -> D1.6. Gestión del Conocimiento y Sostenibilidad | I16: D1.6.1 | J16: Revisión y aprobación de publicaciones | K16: =CONCATENATE(I16,". ",J16) -> D1.6.1. Revisión y aprobación de publicaciones | L16: Número de informes | M16: Informe | N16: Documento de trabajo | O16: Se promueve la sostenibilidad del Programa | U16: 2 | AA16: 3 | AB16: =SUM(P16:AA16) -> 5
A17: R1 | B17: =IFERROR(CONCATENATE(A17,". ",VLOOKUP(A17,'results, prods y acts'!$A$2:$B$8,2,FALSE)),"") -> R1. Los procesos de gestión de gasto corriente vinculados a los servicios básicos priorizados a cargo de los GSN son más eficaces y eficientes | C17: P1 | D17: =IFERROR(CONCATENATE(C17,". ",VLOOKUP(C17,'results, prods y acts'!$D$2:$E$12,2,FALSE)),CONCATENATE(C17,". ")) -> P1. Asistencia técnica | E17: {=IFERROR(INDEX(_xlfn.TEXTSPLIT(I17,"."),2)&"."&INDEX(_xlfn.TEXTSPLIT(I17,"."),3),"")} -> P1.1 | F17: =IFERROR(CONCATENATE(E17,". ",VLOOKUP(E17,'results, prods y acts'!$G$2:$H$16,2,FALSE)),"") -> P1.1. Taller | G17: A nivel GSN | I17: R1.P1.1.1 | J17: Taller en la gestión de la programación, contrataciones y almacén | K17: =CONCATENATE(I17,". ",J17) -> R1.P1.1.1. Taller en la gestión de la programación, contrataciones y almacén | L17: Número de Talleres | M17: Taller | N17: Reporte de Taller | O17: Los GSNs mejoran sus procesos de gestión de abastecimiento | Q17: 1 | S17: 1 | AB17: =SUM(P17:AA17) -> 2
A18: R1 | B18: =IFERROR(CONCATENATE(A18,". ",VLOOKUP(A18,'results, prods y acts'!$A$2:$B$8,2,FALSE)),"") -> R1. Los procesos de gestión de gasto corriente vinculados a los servicios básicos priorizados a cargo de los GSN son más eficaces y eficientes | C18: P1 | D18: =IFERROR(CONCATENATE(C18,". ",VLOOKUP(C18,'results, prods y acts'!$D$2:$E$12,2,FALSE)),CONCATENATE(C18,". ")) -> P1. Asistencia técnica | E18: {=IFERROR(INDEX(_xlfn.TEXTSPLIT(I18,"."),2)&"."&INDEX(_xlfn.TEXTSPLIT(I18,"."),3),"")} -> P1.2 | F18: =IFERROR(CONCATENATE(E18,". ",VLOOKUP(E18,'results, prods y acts'!$G$2:$H$16,2,FALSE)),"") -> P1.2. Acompañamiento | G18: A nivel GSN | I18: R1.P1.2.1 | J18: Acompañamiento a los GSN en el proceso de programación de la demanda de bienes y servicios relacionados a servicios priorizados en educación y salud | K18: =CONCATENATE(I18,". ",J18) -> R1.P1.2.1. Acompañamiento a los GSN en el proceso de programación de la demanda de bienes y servicios relacionados a servicios priorizados en educación y salud | L18: Número de acompañamientos | M18: Acompañamiento | N18: Informe / Ficha de Seguimiento | O18: GSNs optimiza sus procesos de gestión. | P18: 5 | Q18: 4 | R18: 2 | S18: 4 | T18: 4 | V18: 1 | W18: 2 | X18: 3 | Y18: 4 | Z18: 1 | AB18: =SUM(P18:AA18) -> 30
A19: R1 | B19: =IFERROR(CONCATENATE(A19,". ",VLOOKUP(A19,'results, prods y acts'!$A$2:$B$8,2,FALSE)),"") -> R1. Los procesos de gestión de gasto corriente vinculados a los servicios básicos priorizados a cargo de los GSN son más eficaces y eficientes | C19: P1 | D19: =IFERROR(CONCATENATE(C19,". ",VLOOKUP(C19,'results, prods y acts'!$D$2:$E$12,2,FALSE)),CONCATENATE(C19,". ")) -> P1. Asistencia técnica | E19: {=IFERROR(INDEX(_xlfn.TEXTSPLIT(I19,"."),2)&"."&INDEX(_xlfn.TEXTSPLIT(I19,"."),3),"")} -> P1.2 | F19: =IFERROR(CONCATENATE(E19,". ",VLOOKUP(E19,'results, prods y acts'!$G$2:$H$16,2,FALSE)),"") -> P1.2. Acompañamiento | G19: A nivel GSN | I19: R1.P1.2.2 | J19: Acompañamiento a los GSN en las fases de los procesos de contratación de bienes y servicios relacionados al transporte y distribución de vacunas y Sulfato Ferroso | K19: =CONCATENATE(I19,". ",J19) -> R1.P1.2.2. Acompañamiento a los GSN en las fases de los procesos de contratación de bienes y servicios relacionados al transporte y distribución de vacunas y Sulfato Ferroso | L19: Número de acompañamientos | M19: GSN | N19: Ficha de Seguimiento | O19: GSN culminan procesos de contratación de los SBP | P19: 1 | Q19: 1 | R19: 3 | S19: 1 | T19: 1 | U19: 2 | V19: 2 | Y19: 3 | Z19: 2 | AB19: =SUM(P19:AA19) -> 16
A20: R1 | B20: =IFERROR(CONCATENATE(A20,". ",VLOOKUP(A20,'results, prods y acts'!$A$2:$B$8,2,FALSE)),"") -> R1. Los procesos de gestión de gasto corriente vinculados a los servicios básicos priorizados a cargo de los GSN son más eficaces y eficientes | C20: P1 | D20: =IFERROR(CONCATENATE(C20,". ",VLOOKUP(C20,'results, prods y acts'!$D$2:$E$12,2,FALSE)),CONCATENATE(C20,". ")) -> P1. Asistencia técnica | E20: {=IFERROR(INDEX(_xlfn.TEXTSPLIT(I20,"."),2)&"."&INDEX(_xlfn.TEXTSPLIT(I20,"."),3),"")} -> P1.2 | F20: =IFERROR(CONCATENATE(E20,". ",VLOOKUP(E20,'results, prods y acts'!$G$2:$H$16,2,FALSE)),"") -> P1.2. Acompañamiento | G20: A nivel GSN | I20: R1.P1.2.3 | J20: Acompañamiento en el seguimiento del proceso de distribución de vacunas, registro oportuno de entradas y salidas (Neas y PECOSAS) de las vacunas. | K20: =CONCATENATE(I20,". ",J20) -> R1.P1.2.3. Acompañamiento en el seguimiento del proceso de distribución de vacunas, registro oportuno de entradas y salidas (Neas y PECOSAS) de las vacunas. | L20: Número de acompañamientos | M20: Acompañamiento | N20: Ficha de Seguimiento | O20: GSN relacionado con los SBP realiza oportunamente la distribución de vacunas. | P20: 2 | Q20: 4 | R20: 2 | T20: 1 | U20: 4 | V20: 3 | X20: 2 | Z20: 3 | AA20: 2 | AB20: =SUM(P20:AA20) -> 23
A21: R1 | B21: =IFERROR(CONCATENATE(A21,". ",VLOOKUP(A21,'results, prods y acts'!$A$2:$B$8,2,FALSE)),"") -> R1. Los procesos de gestión de gasto corriente vinculados a los servicios básicos priorizados a cargo de los GSN son más eficaces y eficientes | C21: P1 | D21: =IFERROR(CONCATENATE(C21,". ",VLOOKUP(C21,'results, prods y acts'!$D$2:$E$12,2,FALSE)),CONCATENATE(C21,". ")) -> P1. Asistencia técnica | E21: {=IFERROR(INDEX(_xlfn.TEXTSPLIT(I21,"."),2)&"."&INDEX(_xlfn.TEXTSPLIT(I21,"."),3),"")} -> P1.2 | F21: =IFERROR(CONCATENATE(E21,". ",VLOOKUP(E21,'results, prods y acts'!$G$2:$H$16,2,FALSE)),"") -> P1.2. Acompañamiento | G21: A nivel GSN | I21: R1.P1.2.4 | J21: Acompañamiento en el seguimiento del proceso de distribución del sulfato ferroso y verificación del registro oportuno de entradas y salidas (Neas y PECOSAS) del sulfato ferroso | K21: =CONCATENATE(I21,". ",J21) -> R1.P1.2.4. Acompañamiento en el seguimiento del proceso de distribución del sulfato ferroso y verificación del registro oportuno de entradas y salidas (Neas y PECOSAS) del sulfato ferroso | L21: Número de acompañamientos | M21: Acompañamiento | N21: Ficha de Seguimiento | O21: GSN relacionados a los SBP realiza oportunamente la distribución del sulfato ferroso | P21: 1 | Q21: 2 | R21: 4 | T21: 1 | U21: 3 | V21: 3 | X21: 2 | Y21: 2 | Z21: 3 | AA21: 1 | AB21: =SUM(P21:AA21) -> 22
A22: R1 | B22: =IFERROR(CONCATENATE(A22,". ",VLOOKUP(A22,'results, prods y acts'!$A$2:$B$8,2,FALSE)),"") -> R1. Los procesos de gestión de gasto corriente vinculados a los servicios básicos priorizados a cargo de los GSN son más eficaces y eficientes | C22: P1 | D22: =IFERROR(CONCATENATE(C22,". ",VLOOKUP(C22,'results, prods y acts'!$D$2:$E$12,2,FALSE)),CONCATENATE(C22,". ")) -> P1. Asistencia técnica | E22: {=IFERROR(INDEX(_xlfn.TEXTSPLIT(I22,"."),2)&"."&INDEX(_xlfn.TEXTSPLIT(I22,"."),3),"")} -> P1.2 | F22: =IFERROR(CONCATENATE(E22,". ",VLOOKUP(E22,'results, prods y acts'!$G$2:$H$16,2,FALSE)),"") -> P1.2. Acompañamiento | G22: A nivel GSN | I22: R1.P1.2.5 | J22: Acompañamiento a los GSN en las fases de los procesos de contratación de bienes y servicios relacionados al transporte y distribución de material educativo. | K22: =CONCATENATE(I22,". ",J22) -> R1.P1.2.5. Acompañamiento a los GSN en las fases de los procesos de contratación de bienes y servicios relacionados al transporte y distribución de material educativo. | L22: Número de acompañamientos | M22: Acompañamiento | N22: Ficha de Seguimiento | O22: GSN culminan procesos de contratación de los SBP | P22: 1 | Q22: 11 | R22: 1 | V22: 1 | W22: 2 | Z22: 9 | AA22: 1 | AB22: =SUM(P22:AA22) -> 26
A23: R1 | B23: =IFERROR(CONCATENATE(A23,". ",VLOOKUP(A23,'results, prods y acts'!$A$2:$B$8,2,FALSE)),"") -> R1. Los procesos de gestión de gasto corriente vinculados a los servicios básicos priorizados a cargo de los GSN son más eficaces y eficientes | C23: P1 | D23: =IFERROR(CONCATENATE(C23,". ",VLOOKUP(C23,'results, prods y acts'!$D$2:$E$12,2,FALSE)),CONCATENATE(C23,". ")) -> P1. Asistencia técnica | E23: {=IFERROR(INDEX(_xlfn.TEXTSPLIT(I23,"."),2)&"."&INDEX(_xlfn.TEXTSPLIT(I23,"."),3),"")} -> P1.2 | F23: =IFERROR(CONCATENATE(E23,". ",VLOOKUP(E23,'results, prods y acts'!$G$2:$H$16,2,FALSE)),"") -> P1.2. Acompañamiento | G23: A nivel GSN | I23: R1.P1.2.6 | J23: Acompañamiento en el seguimiento del proceso de distribución del material educativo y verificación del registro oportuno de entradas y salidas (Neas y PECOSAS) del material educativo. | K23: =CONCATENATE(I23,". ",J23) -> R1.P1.2.6. Acompañamiento en el seguimiento del proceso de distribución del material educativo y verificación del registro oportuno de entradas y salidas (Neas y PECOSAS) del material educativo. | L23: Número de acompañamientos | M23: Acompañamiento | N23: Ficha de Seguimiento | O23: GSN relacionados a los SBP realiza oportunamente la distribución del material educativo | P23: 1 | Q23: 1 | R23: 5 | S23: 7 | T23: 3 | U23: 3 | V23: 1 | X23: 4 | Y23: 2 | AB23: =SUM(P23:AA23) -> 27
A24: R1 | B24: =IFERROR(CONCATENATE(A24,". ",VLOOKUP(A24,'results, prods y acts'!$A$2:$B$8,2,FALSE)),"") -> R1. Los procesos de gestión de gasto corriente vinculados a los servicios básicos priorizados a cargo de los GSN son más eficaces y eficientes | C24: P1 | D24: =IFERROR(CONCATENATE(C24,". ",VLOOKUP(C24,'results, prods y acts'!$D$2:$E$12,2,FALSE)),CONCATENATE(C24,". ")) -> P1. Asistencia técnica | E24: {=IFERROR(INDEX(_xlfn.TEXTSPLIT(I24,"."),2)&"."&INDEX(_xlfn.TEXTSPLIT(I24,"."),3),"")} -> P1.2 | F24: =IFERROR(CONCATENATE(E24,". ",VLOOKUP(E24,'results, prods y acts'!$G$2:$H$16,2,FALSE)),"") -> P1.2. Acompañamiento | G24: A nivel GSN | I24: R1.P1.2.7 | J24: Acompañamiento a los GSNs en el proceso del seguimiento de la ejecución presupuestaria de ingresos y gastos. | K24: =CONCATENATE(I24,". ",J24) -> R1.P1.2.7. Acompañamiento a los GSNs en el proceso del seguimiento de la ejecución presupuestaria de ingresos y gastos. | L24: Número de acompañamientos | M24: Acompañamiento | N24: Ficha de Seguimiento | O24: Los GSNs se encuentran alertados sobre los avances en la ejecución presupuestaria. | R24: 4 | S24: 1 | T24: 3 | U24: 1 | V24: 2 | W24: 4 | Y24: 5 | Z24: 3 | AA24: 1 | AB24: =SUM(P24:AA24) -> 24
A25: R1 | B25: =IFERROR(CONCATENATE(A25,". ",VLOOKUP(A25,'results, prods y acts'!$A$2:$B$8,2,FALSE)),"") -> R1. Los procesos de gestión de gasto corriente vinculados a los servicios básicos priorizados a cargo de los GSN son más eficaces y eficientes | C25: P1 | D25: =IFERROR(CONCATENATE(C25,". ",VLOOKUP(C25,'results, prods y acts'!$D$2:$E$12,2,FALSE)),CONCATENATE(C25,". ")) -> P1. Asistencia técnica | E25: {=IFERROR(INDEX(_xlfn.TEXTSPLIT(I25,"."),2)&"."&INDEX(_xlfn.TEXTSPLIT(I25,"."),3),"")} -> P1.2 | F25: =IFERROR(CONCATENATE(E25,". ",VLOOKUP(E25,'results, prods y acts'!$G$2:$H$16,2,FALSE)),"") -> P1.2. Acompañamiento | G25: A nivel GSN | I25: R1.P1.2.8 | J25: Acompañamiento a los responsables designados en la elaboración del Plan de trabajo para la implementación de mejora de los almacenes relacionados a los SBP. | K25: =CONCATENATE(I25,". ",J25) -> R1.P1.2.8. Acompañamiento a los responsables designados en la elaboración del Plan de trabajo para la implementación de mejora de los almacenes relacionados a los SBP. | L25: Número de acompañamientos | M25: Acompañamiento | N25: Ficha de Seguimiento | O25: UEs de sector de Educación y/o Salud cuentan con plan de trabajo elaborado para la mejora de los almacenes a los SBP | Q25: 4 | R25: 3 | S25: 4 | T25: 2 | V25: 1 | W25: 4 | X25: 1 | Y25: 1 | AB25: =SUM(P25:AA25) -> 20
A26: R1 | B26: =IFERROR(CONCATENATE(A26,". ",VLOOKUP(A26,'results, prods y acts'!$A$2:$B$8,2,FALSE)),"") -> R1. Los procesos de gestión de gasto corriente vinculados a los servicios básicos priorizados a cargo de los GSN son más eficaces y eficientes | C26: P1 | D26: =IFERROR(CONCATENATE(C26,". ",VLOOKUP(C26,'results, prods y acts'!$D$2:$E$12,2,FALSE)),CONCATENATE(C26,". ")) -> P1. Asistencia técnica | E26: {=IFERROR(INDEX(_xlfn.TEXTSPLIT(I26,"."),2)&"."&INDEX(_xlfn.TEXTSPLIT(I26,"."),3),"")} -> P1.2 | F26: =IFERROR(CONCATENATE(E26,". ",VLOOKUP(E26,'results, prods y acts'!$G$2:$H$16,2,FALSE)),"") -> P1.2. Acompañamiento | G26: A nivel GSN | I26: R1.P1.2.9 | J26: Acompañamiento a los responsables designados en el proceso de implementación del Plan de trabajo de mejora de los almacenes relacionados a los SBP. | K26: =CONCATENATE(I26,". ",J26) -> R1.P1.2.9. Acompañamiento a los responsables designados en el proceso de implementación del Plan de trabajo de mejora de los almacenes relacionados a los SBP. | L26: Número de acompañamientos | M26: Acompañamiento | N26: Ficha de Seguimiento | O26: UEs de sector de Educación y/o Salud implementan mejoras en los almacenes. | P26: 3 | Q26: 11 | R26: 2 | S26: 2 | T26: 1 | U26: 2 | V26: 3 | W26: 1 | X26: 2 | Z26: 2 | AB26: =SUM(P26:AA26) -> 29
A27: R1 | B27: =IFERROR(CONCATENATE(A27,". ",VLOOKUP(A27,'results, prods y acts'!$A$2:$B$8,2,FALSE)),"") -> R1. Los procesos de gestión de gasto corriente vinculados a los servicios básicos priorizados a cargo de los GSN son más eficaces y eficientes | C27: P1 | D27: =IFERROR(CONCATENATE(C27,". ",VLOOKUP(C27,'results, prods y acts'!$D$2:$E$12,2,FALSE)),CONCATENATE(C27,". ")) -> P1. Asistencia técnica | E27: {=IFERROR(INDEX(_xlfn.TEXTSPLIT(I27,"."),2)&"."&INDEX(_xlfn.TEXTSPLIT(I27,"."),3),"")} -> P1.2 | F27: =IFERROR(CONCATENATE(E27,". ",VLOOKUP(E27,'results, prods y acts'!$G$2:$H$16,2,FALSE)),"") -> P1.2. Acompañamiento | G27: A nivel GSN | I27: R1.P1.2.11 | J27: Acompañamiento a los GSN en el proceso de planificación de las ACR | K27: =CONCATENATE(I27,". ",J27) -> R1.P1.2.11. Acompañamiento a los GSN en el proceso de planificación de las ACR | L27: Número de acompañamientos | M27: Acompañamiento | N27: Ficha de Seguimiento | O27: Plan Operativo (POI) de SERNANP aprobado | S27: 3 | AB27: =SUM(P27:AA27) -> 3
A28: R1 | B28: =IFERROR(CONCATENATE(A28,". ",VLOOKUP(A28,'results, prods y acts'!$A$2:$B$8,2,FALSE)),"") -> R1. Los procesos de gestión de gasto corriente vinculados a los servicios básicos priorizados a cargo de los GSN son más eficaces y eficientes | C28: P1 | D28: =IFERROR(CONCATENATE(C28,". ",VLOOKUP(C28,'results, prods y acts'!$D$2:$E$12,2,FALSE)),CONCATENATE(C28,". ")) -> P1. Asistencia técnica | E28: {=IFERROR(INDEX(_xlfn.TEXTSPLIT(I28,"."),2)&"."&INDEX(_xlfn.TEXTSPLIT(I28,"."),3),"")} -> P1.2 | F28: =IFERROR(CONCATENATE(E28,". ",VLOOKUP(E28,'results, prods y acts'!$G$2:$H$16,2,FALSE)),"") -> P1.2. Acompañamiento | G28: A nivel GSN | I28: R1.P1.2.12 | J28: Acompañamiento a los GSN en el proceso de programación de la demanda de bienes y servicios relacionados a los ACR | K28: =CONCATENATE(I28,". ",J28) -> R1.P1.2.12. Acompañamiento a los GSN en el proceso de programación de la demanda de bienes y servicios relacionados a los ACR | L28: Número de acompañamientos | M28: Acompañamiento | N28: Informe / Ficha de Seguimiento | O28: GSNs optimiza sus procesos de gestión. | T28: 3 | X28: 3 | AB28: =SUM(P28:AA28) -> 6
A29: R1 | B29: =IFERROR(CONCATENATE(A29,". ",VLOOKUP(A29,'results, prods y acts'!$A$2:$B$8,2,FALSE)),"") -> R1. Los procesos de gestión de gasto corriente vinculados a los servicios básicos priorizados a cargo de los GSN son más eficaces y eficientes | C29: P1 | D29: =IFERROR(CONCATENATE(C29,". ",VLOOKUP(C29,'results, prods y acts'!$D$2:$E$12,2,FALSE)),CONCATENATE(C29,". ")) -> P1. Asistencia técnica | E29: {=IFERROR(INDEX(_xlfn.TEXTSPLIT(I29,"."),2)&"."&INDEX(_xlfn.TEXTSPLIT(I29,"."),3),"")} -> P1.2 | F29: =IFERROR(CONCATENATE(E29,". ",VLOOKUP(E29,'results, prods y acts'!$G$2:$H$16,2,FALSE)),"") -> P1.2. Acompañamiento | G29: A nivel GSN | I29: R1.P1.2.13 | J29: Acompañamiento a los GSN en las fases de los procesos de contratación de bienes y servicios relacionados con las actividades de las ACR | K29: =CONCATENATE(I29,". ",J29) -> R1.P1.2.13. Acompañamiento a los GSN en las fases de los procesos de contratación de bienes y servicios relacionados con las actividades de las ACR | L29: Número de acompañamientos | M29: GSN | N29: Ficha de Seguimiento | O29: GSN culminan procesos de contratación de los SBP | T29: 3 | V29: 3 | Y29: 3 | AB29: =SUM(P29:AA29) -> 9
A30: R1 | B30: =IFERROR(CONCATENATE(A30,". ",VLOOKUP(A30,'results, prods y acts'!$A$2:$B$8,2,FALSE)),"") -> R1. Los procesos de gestión de gasto corriente vinculados a los servicios básicos priorizados a cargo de los GSN son más eficaces y eficientes | C30: P1 | D30: =IFERROR(CONCATENATE(C30,". ",VLOOKUP(C30,'results, prods y acts'!$D$2:$E$12,2,FALSE)),CONCATENATE(C30,". ")) -> P1. Asistencia técnica | E30: {=IFERROR(INDEX(_xlfn.TEXTSPLIT(I30,"."),2)&"."&INDEX(_xlfn.TEXTSPLIT(I30,"."),3),"")} -> P1.2 | F30: =IFERROR(CONCATENATE(E30,". ",VLOOKUP(E30,'results, prods y acts'!$G$2:$H$16,2,FALSE)),"") -> P1.2. Acompañamiento | G30: A nivel GSN | I30: R1.P1.2.14 | J30: Acompañamiento a los GSNs en el proceso del seguimiento de la ejecución presupuestaria de gastos de las ACR | K30: =CONCATENATE(I30,". ",J30) -> R1.P1.2.14. Acompañamiento a los GSNs en el proceso del seguimiento de la ejecución presupuestaria de gastos de las ACR | L30: Número de acompañamientos | M30: Acompañamiento | N30: Ficha de Seguimiento | O30: Los GSNs se encuentran alertados sobre los avances en la ejecución presupuestaria. | U30: 3 | X30: 3 | AB30: =SUM(P30:AA30) -> 6
A31: R1 | B31: =IFERROR(CONCATENATE(A31,". ",VLOOKUP(A31,'results, prods y acts'!$A$2:$B$8,2,FALSE)),"") -> R1. Los procesos de gestión de gasto corriente vinculados a los servicios básicos priorizados a cargo de los GSN son más eficaces y eficientes | C31: P1 | D31: =IFERROR(CONCATENATE(C31,". ",VLOOKUP(C31,'results, prods y acts'!$D$2:$E$12,2,FALSE)),CONCATENATE(C31,". ")) -> P1. Asistencia técnica | E31: {=IFERROR(INDEX(_xlfn.TEXTSPLIT(I31,"."),2)&"."&INDEX(_xlfn.TEXTSPLIT(I31,"."),3),"")} -> P1.2 | F31: =IFERROR(CONCATENATE(E31,". ",VLOOKUP(E31,'results, prods y acts'!$G$2:$H$16,2,FALSE)),"") -> P1.2. Acompañamiento | G31: A nivel GSN | I31: R1.P1.2.15 | J31: Acompañamiento a los GSN en la elaboración de la metodología de evaluación de las finanzas públicas (PEFA) | K31: =CONCATENATE(I31,". ",J31) -> R1.P1.2.15. Acompañamiento a los GSN en la elaboración de la metodología de evaluación de las finanzas públicas (PEFA) | L31: Número de acompañamientos | M31: Acompañamiento | N31: Ficha de Seguimiento | O31: GSN cuentan con metodología de evaluación de las finanzas públicas (PEFA) | Z31: 10 | AB31: =SUM(P31:AA31) -> 10
A32: R1 | B32: =IFERROR(CONCATENATE(A32,". ",VLOOKUP(A32,'results, prods y acts'!$A$2:$B$8,2,FALSE)),"") -> R1. Los procesos de gestión de gasto corriente vinculados a los servicios básicos priorizados a cargo de los GSN son más eficaces y eficientes | C32: P1 | D32: =IFERROR(CONCATENATE(C32,". ",VLOOKUP(C32,'results, prods y acts'!$D$2:$E$12,2,FALSE)),CONCATENATE(C32,". ")) -> P1. Asistencia técnica | E32: {=IFERROR(INDEX(_xlfn.TEXTSPLIT(I32,"."),2)&"."&INDEX(_xlfn.TEXTSPLIT(I32,"."),3),"")} -> P1.3 | F32: =IFERROR(CONCATENATE(E32,". ",VLOOKUP(E32,'results, prods y acts'!$G$2:$H$16,2,FALSE)),"") -> P1.3. Reuniones de retroalimentación | G32: A nivel GSN | I32: R1.P1.3.1 | J32: Reuniones de retroalimentación del avance y resultado de la distribución de vacunas y material educativo con los GSN. | K32: =CONCATENATE(I32,". ",J32) -> R1.P1.3.1. Reuniones de retroalimentación del avance y resultado de la distribución de vacunas y material educativo con los GSN. | L32: Número de reuniones | M32: Reunión | N32: Ficha de Seguimiento | O32: UEs - Sector Educación y Salud, informado y alertado de los avances y resultados de la distribución de vacunas y material educativo. | Q32: 3 | R32: 3 | S32: 3 | U32: 3 | V32: 1 | W32: 1 | X32: 2 | Y32: 1 | Z32: 2 | AA32: 1 | AB32: =SUM(P32:AA32) -> 20
A33: R1 | B33: =IFERROR(CONCATENATE(A33,". ",VLOOKUP(A33,'results, prods y acts'!$A$2:$B$8,2,FALSE)),"") -> R1. Los procesos de gestión de gasto corriente vinculados a los servicios básicos priorizados a cargo de los GSN son más eficaces y eficientes | C33: P2 | D33: =IFERROR(CONCATENATE(C33,". ",VLOOKUP(C33,'results, prods y acts'!$D$2:$E$12,2,FALSE)),CONCATENATE(C33,". ")) -> P2. Fortalecimiento de capacidades | E33: {=IFERROR(INDEX(_xlfn.TEXTSPLIT(I33,"."),2)&"."&INDEX(_xlfn.TEXTSPLIT(I33,"."),3),"")} -> P2.1 | F33: =IFERROR(CONCATENATE(E33,". ",VLOOKUP(E33,'results, prods y acts'!$G$2:$H$16,2,FALSE)),"") -> P2.1. Cursos | G33: A nivel GSN | I33: R1.P2.1.1 | J33: Curso (Programa Especial) en temas relacionados con la cadena de abastecimiento. | K33: =CONCATENATE(I33,". ",J33) -> R1.P2.1.1. Curso (Programa Especial) en temas relacionados con la cadena de abastecimiento. | L33: Número de cursos | M33: Curso | N33: Informe | O33: Fortalecer conocimiento sobre metas de la cadena de abastecimiento. | V33: 1 | AB33: =SUM(P33:AA33) -> 1
A34: R1 | B34: =IFERROR(CONCATENATE(A34,". ",VLOOKUP(A34,'results, prods y acts'!$A$2:$B$8,2,FALSE)),"") -> R1. Los procesos de gestión de gasto corriente vinculados a los servicios básicos priorizados a cargo de los GSN son más eficaces y eficientes | C34: P2 | D34: =IFERROR(CONCATENATE(C34,". ",VLOOKUP(C34,'results, prods y acts'!$D$2:$E$12,2,FALSE)),CONCATENATE(C34,". ")) -> P2. Fortalecimiento de capacidades | E34: {=IFERROR(INDEX(_xlfn.TEXTSPLIT(I34,"."),2)&"."&INDEX(_xlfn.TEXTSPLIT(I34,"."),3),"")} -> P2.1 | F34: =IFERROR(CONCATENATE(E34,". ",VLOOKUP(E34,'results, prods y acts'!$G$2:$H$16,2,FALSE)),"") -> P2.1. Cursos | G34: A nivel GSN | I34: R1.P2.1.2 | J34: Curso en Instrumentos de Sostenibilidad Financiera | K34: =CONCATENATE(I34,". ",J34) -> R1.P2.1.2. Curso en Instrumentos de Sostenibilidad Financiera | L34: Número de cursos | M34: Curso | N34: Informe | O34: Gerencias de recursos naturales capacitados en el uso de instrumentos de sostenibilidad financiera | Q34: 1 | AB34: =SUM(P34:AA34) -> 1
A35: R1 | B35: =IFERROR(CONCATENATE(A35,". ",VLOOKUP(A35,'results, prods y acts'!$A$2:$B$8,2,FALSE)),"") -> R1. Los procesos de gestión de gasto corriente vinculados a los servicios básicos priorizados a cargo de los GSN son más eficaces y eficientes | C35: P2 | D35: =IFERROR(CONCATENATE(C35,". ",VLOOKUP(C35,'results, prods y acts'!$D$2:$E$12,2,FALSE)),CONCATENATE(C35,". ")) -> P2. Fortalecimiento de capacidades | E35: {=IFERROR(INDEX(_xlfn.TEXTSPLIT(I35,"."),2)&"."&INDEX(_xlfn.TEXTSPLIT(I35,"."),3),"")} -> P2.3 | F35: =IFERROR(CONCATENATE(E35,". ",VLOOKUP(E35,'results, prods y acts'!$G$2:$H$16,2,FALSE)),"") -> P2.3. Capacitación ad hoc | G35: A nivel GSN | I35: R1.P2.3.1 | J35: Capacitación ad hoc para la programación de bienes y servicios de los SBP | K35: =CONCATENATE(I35,". ",J35) -> R1.P2.3.1. Capacitación ad hoc para la programación de bienes y servicios de los SBP | L35: Número de capacitaciones | M35: Capacitación | N35: Informe y Actas | O35: Personal técnico involucrado en la programación de CMN se encuentran capacitados en el GSN. | P35: 1 | Q35: 3 | R35: 3 | V35: 2 | W35: 1 | AB35: =SUM(P35:AA35) -> 10
A36: R1 | B36: =IFERROR(CONCATENATE(A36,". ",VLOOKUP(A36,'results, prods y acts'!$A$2:$B$8,2,FALSE)),"") -> R1. Los procesos de gestión de gasto corriente vinculados a los servicios básicos priorizados a cargo de los GSN son más eficaces y eficientes | C36: P2 | D36: =IFERROR(CONCATENATE(C36,". ",VLOOKUP(C36,'results, prods y acts'!$D$2:$E$12,2,FALSE)),CONCATENATE(C36,". ")) -> P2. Fortalecimiento de capacidades | E36: {=IFERROR(INDEX(_xlfn.TEXTSPLIT(I36,"."),2)&"."&INDEX(_xlfn.TEXTSPLIT(I36,"."),3),"")} -> P2.3 | F36: =IFERROR(CONCATENATE(E36,". ",VLOOKUP(E36,'results, prods y acts'!$G$2:$H$16,2,FALSE)),"") -> P2.3. Capacitación ad hoc | G36: A nivel GSN | I36: R1.P2.3.2 | J36: Capacitación ad hoc o Curso de capacidades en la fases de contratación de bienes y servicios vinculados con los SBP | K36: =CONCATENATE(I36,". ",J36) -> R1.P2.3.2. Capacitación ad hoc o Curso de capacidades en la fases de contratación de bienes y servicios vinculados con los SBP | L36: Número de capacitaciones | M36: Curso y/o capacitación | N36: Informe y Actas | O36: Personal del OEC del GSN, se encuentran capacitados. | R36: 2 | T36: 4 | U36: 1 | V36: 3 | AB36: =SUM(P36:AA36) -> 10
A37: R1 | B37: =IFERROR(CONCATENATE(A37,". ",VLOOKUP(A37,'results, prods y acts'!$A$2:$B$8,2,FALSE)),"") -> R1. Los procesos de gestión de gasto corriente vinculados a los servicios básicos priorizados a cargo de los GSN son más eficaces y eficientes | C37: P2 | D37: =IFERROR(CONCATENATE(C37,". ",VLOOKUP(C37,'results, prods y acts'!$D$2:$E$12,2,FALSE)),CONCATENATE(C37,". ")) -> P2. Fortalecimiento de capacidades | E37: {=IFERROR(INDEX(_xlfn.TEXTSPLIT(I37,"."),2)&"."&INDEX(_xlfn.TEXTSPLIT(I37,"."),3),"")} -> P2.3 | F37: =IFERROR(CONCATENATE(E37,". ",VLOOKUP(E37,'results, prods y acts'!$G$2:$H$16,2,FALSE)),"") -> P2.3. Capacitación ad hoc | G37: A nivel GSN | I37: R1.P2.3.3 | J37: Capacitación ad hoc en Gestión de Almacenes de los SBP | K37: =CONCATENATE(I37,". ",J37) -> R1.P2.3.3. Capacitación ad hoc en Gestión de Almacenes de los SBP | L37: Número de capacitaciones | M37: Capacitación | N37: Informe y Actas | O37: Personal técnico involucrado en la gestión de almacenes encuentren capacitados en el GSN | R37: 1 | S37: 1 | W37: 1 | Y37: 2 | AB37: =SUM(P37:AA37) -> 5
A38: R1 | B38: =IFERROR(CONCATENATE(A38,". ",VLOOKUP(A38,'results, prods y acts'!$A$2:$B$8,2,FALSE)),"") -> R1. Los procesos de gestión de gasto corriente vinculados a los servicios básicos priorizados a cargo de los GSN son más eficaces y eficientes | C38: P2 | D38: =IFERROR(CONCATENATE(C38,". ",VLOOKUP(C38,'results, prods y acts'!$D$2:$E$12,2,FALSE)),CONCATENATE(C38,". ")) -> P2. Fortalecimiento de capacidades | E38: {=IFERROR(INDEX(_xlfn.TEXTSPLIT(I38,"."),2)&"."&INDEX(_xlfn.TEXTSPLIT(I38,"."),3),"")} -> P2.5 | F38: =IFERROR(CONCATENATE(E38,". ",VLOOKUP(E38,'results, prods y acts'!$G$2:$H$16,2,FALSE)),"") -> P2.5. Charla | G38: A nivel GSN | I38: R1.P2.5.1 | J38: Charla para la elaboración del PAC 2023, PMBSyO 2024-2026, adecuada elaboración de las solicitudes de pedido, elaboración de especificaciones técnicas y términos de referencia para bienes y servicios y almacenes de los SBP | K38: =CONCATENATE(I38,". ",J38) -> R1.P2.5.1. Charla para la elaboración del PAC 2023, PMBSyO 2024-2026, adecuada elaboración de las solicitudes de pedido, elaboración de especificaciones técnicas y términos de referencia para bienes y servicios y almacenes de los SBP | L38: Número de charlas | M38: Charla | N38: Ficha de Seguimiento | O38: Personal de los GSN responsable de realizar pedidos se encuentra capacitado (Charla virtual). | P38: 2 | Q38: 6 | R38: 3 | S38: 2 | T38: 1 | V38: 6 | W38: 4 | X38: 1 | Y38: 1 | Z38: 1 | AB38: =SUM(P38:AA38) -> 27
A39: R1 | B39: =IFERROR(CONCATENATE(A39,". ",VLOOKUP(A39,'results, prods y acts'!$A$2:$B$8,2,FALSE)),"") -> R1. Los procesos de gestión de gasto corriente vinculados a los servicios básicos priorizados a cargo de los GSN son más eficaces y eficientes | C39: P2 | D39: =IFERROR(CONCATENATE(C39,". ",VLOOKUP(C39,'results, prods y acts'!$D$2:$E$12,2,FALSE)),CONCATENATE(C39,". ")) -> P2. Fortalecimiento de capacidades | E39: {=IFERROR(INDEX(_xlfn.TEXTSPLIT(I39,"."),2)&"."&INDEX(_xlfn.TEXTSPLIT(I39,"."),3),"")} -> P2.5 | F39: =IFERROR(CONCATENATE(E39,". ",VLOOKUP(E39,'results, prods y acts'!$G$2:$H$16,2,FALSE)),"") -> P2.5. Charla | G39: A nivel GSN | I39: R1.P2.5.2 | J39: Charla para la elaboración del POI, PMBSyO 2027-2029, adecuada elaboración de las solicitudes de pedido, elaboración de especificaciones técnicas y términos de referencia para bienes y servicios para ACR | K39: =CONCATENATE(I39,". ",J39) -> R1.P2.5.2. Charla para la elaboración del POI, PMBSyO 2027-2029, adecuada elaboración de las solicitudes de pedido, elaboración de especificaciones técnicas y términos de referencia para bienes y servicios para ACR | L39: Número de charlas | M39: Charla | N39: Ficha de Seguimiento | O39: Personal de las ACR responsable de realizar pedidos se encuentra capacitado (Charla virtual). | Q39: 3 | V39: 3 | AB39: =SUM(P39:AA39) -> 6
A40: R1 | B40: =IFERROR(CONCATENATE(A40,". ",VLOOKUP(A40,'results, prods y acts'!$A$2:$B$8,2,FALSE)),"") -> R1. Los procesos de gestión de gasto corriente vinculados a los servicios básicos priorizados a cargo de los GSN son más eficaces y eficientes | C40: P2 | D40: =IFERROR(CONCATENATE(C40,". ",VLOOKUP(C40,'results, prods y acts'!$D$2:$E$12,2,FALSE)),CONCATENATE(C40,". ")) -> P2. Fortalecimiento de capacidades | E40: {=IFERROR(INDEX(_xlfn.TEXTSPLIT(I40,"."),2)&"."&INDEX(_xlfn.TEXTSPLIT(I40,"."),3),"")} -> P2.5 | F40: =IFERROR(CONCATENATE(E40,". ",VLOOKUP(E40,'results, prods y acts'!$G$2:$H$16,2,FALSE)),"") -> P2.5. Charla | G40: A nivel GSN | I40: R1.P2.5.3 | J40: Charla especializada en Presupuesto Público | K40: =CONCATENATE(I40,". ",J40) -> R1.P2.5.3. Charla especializada en Presupuesto Público | L40: Número de charlas | M40: Charla | N40: Ficha de Seguimiento | O40: Personal del Ministerio Público capacitado | R40: 1 | V40: 1 | AB40: =SUM(P40:AA40) -> 2
A41: R1 | B41: =IFERROR(CONCATENATE(A41,". ",VLOOKUP(A41,'results, prods y acts'!$A$2:$B$8,2,FALSE)),"") -> R1. Los procesos de gestión de gasto corriente vinculados a los servicios básicos priorizados a cargo de los GSN son más eficaces y eficientes | C41: P3 | D41: =IFERROR(CONCATENATE(C41,". ",VLOOKUP(C41,'results, prods y acts'!$D$2:$E$12,2,FALSE)),CONCATENATE(C41,". ")) -> P3. Instrumentos de mejora de la gestión | E41: {=IFERROR(INDEX(_xlfn.TEXTSPLIT(I41,"."),2)&"."&INDEX(_xlfn.TEXTSPLIT(I41,"."),3),"")} -> P3.1 | F41: =IFERROR(CONCATENATE(E41,". ",VLOOKUP(E41,'results, prods y acts'!$G$2:$H$16,2,FALSE)),"") | G41: A nivel GSN | I41: R1.P3.1.1 | J41: Propuesta de protocolo en base a la normatividad de los entes rectores para mejorar la gestión del abastecimiento | K41: =CONCATENATE(I41,". ",J41) -> R1.P3.1.1. Propuesta de protocolo en base a la normatividad de los entes rectores para mejorar la gestión del abastecimiento | L41: Número de propuestas | M41: Propuesta | N41: Informe | O41: GSN utiliza TI en su gestion del abastecimiento | R41: 1 | T41: 1 | X41: 2 | AB41: =SUM(P41:AA41) -> 4
A42: R1 | B42: =IFERROR(CONCATENATE(A42,". ",VLOOKUP(A42,'results, prods y acts'!$A$2:$B$8,2,FALSE)),"") -> R1. Los procesos de gestión de gasto corriente vinculados a los servicios básicos priorizados a cargo de los GSN son más eficaces y eficientes | C42: P3 | D42: =IFERROR(CONCATENATE(C42,". ",VLOOKUP(C42,'results, prods y acts'!$D$2:$E$12,2,FALSE)),CONCATENATE(C42,". ")) -> P3. Instrumentos de mejora de la gestión | E42: {=IFERROR(INDEX(_xlfn.TEXTSPLIT(I42,"."),2)&"."&INDEX(_xlfn.TEXTSPLIT(I42,"."),3),"")} -> P3.1 | F42: =IFERROR(CONCATENATE(E42,". ",VLOOKUP(E42,'results, prods y acts'!$G$2:$H$16,2,FALSE)),"") | G42: A nivel GSN | I42: R1.P3.1.2 | J42: Acompañamiento en la actualización de instrumentos de gestión de la cadena de abastecimiento publico de los SBP | K42: =CONCATENATE(I42,". ",J42) -> R1.P3.1.2. Acompañamiento en la actualización de instrumentos de gestión de la cadena de abastecimiento publico de los SBP | L42: Número de acompañamientos | M42: Acompañamiento | N42: Ficha de Seguimiento | O42: GSNs optimiza sus procesos de gestión. | Q42: 1 | S42: 1 | W42: 1 | X42: 1 | Z42: 1 | AB42: =SUM(P42:AA42) -> 5
A43: R1 | B43: =IFERROR(CONCATENATE(A43,". ",VLOOKUP(A43,'results, prods y acts'!$A$2:$B$8,2,FALSE)),"") -> R1. Los procesos de gestión de gasto corriente vinculados a los servicios básicos priorizados a cargo de los GSN son más eficaces y eficientes | C43: P3 | D43: =IFERROR(CONCATENATE(C43,". ",VLOOKUP(C43,'results, prods y acts'!$D$2:$E$12,2,FALSE)),CONCATENATE(C43,". ")) -> P3. Instrumentos de mejora de la gestión | E43: {=IFERROR(INDEX(_xlfn.TEXTSPLIT(I43,"."),2)&"."&INDEX(_xlfn.TEXTSPLIT(I43,"."),3),"")} -> P3.5 | F43: =IFERROR(CONCATENATE(E43,". ",VLOOKUP(E43,'results, prods y acts'!$G$2:$H$16,2,FALSE)),"") -> P3.5. Propuesta de modificación técnico-administrativa a nivel sectorial | G43: A nivel GSN | I43: R1.P3.5.1 | J43: Seguimiento de validación de plantilla de AO para PP0057 | K43: =CONCATENATE(I43,". ",J43) -> R1.P3.5.1. Seguimiento de validación de plantilla de AO para PP0057 | L43: Número de propuestas | M43: Propuesta | N43: Informe | O43: Plantilla estandar validada de AO del PP0057 | R43: 1 | AB43: =SUM(P43:AA43) -> 1
A44: R1 | B44: =IFERROR(CONCATENATE(A44,". ",VLOOKUP(A44,'results, prods y acts'!$A$2:$B$8,2,FALSE)),"") -> R1. Los procesos de gestión de gasto corriente vinculados a los servicios básicos priorizados a cargo de los GSN son más eficaces y eficientes | C44: P4 | D44: =IFERROR(CONCATENATE(C44,". ",VLOOKUP(C44,'results, prods y acts'!$D$2:$E$12,2,FALSE)),CONCATENATE(C44,". ")) -> P4. Tecnologia de la Informacion / Instrumentos de innovación | E44: {=IFERROR(INDEX(_xlfn.TEXTSPLIT(I44,"."),2)&"."&INDEX(_xlfn.TEXTSPLIT(I44,"."),3),"")} -> P4.1 | F44: =IFERROR(CONCATENATE(E44,". ",VLOOKUP(E44,'results, prods y acts'!$G$2:$H$16,2,FALSE)),"") -> P4.1. Estrategia para la eficiencia de procesos | G44: A nivel GSN | I44: R1.P4.1.1 | J44: Implementacion de TI en la gestion del Abastecimiento | K44: =CONCATENATE(I44,". ",J44) -> R1.P4.1.1. Implementacion de TI en la gestion del Abastecimiento | L44: Número de propuesta | M44: Propuesta | N44: Informe | O44: GSN utiliza TI en su gestion del abastecimiento | S44: 1 | AB44: =SUM(P44:AA44) -> 1
A45: R1 | B45: =IFERROR(CONCATENATE(A45,". ",VLOOKUP(A45,'results, prods y acts'!$A$2:$B$8,2,FALSE)),"") -> R1. Los procesos de gestión de gasto corriente vinculados a los servicios básicos priorizados a cargo de los GSN son más eficaces y eficientes | C45: P4 | D45: =IFERROR(CONCATENATE(C45,". ",VLOOKUP(C45,'results, prods y acts'!$D$2:$E$12,2,FALSE)),CONCATENATE(C45,". ")) -> P4. Tecnologia de la Informacion / Instrumentos de innovación | E45: {=IFERROR(INDEX(_xlfn.TEXTSPLIT(I45,"."),2)&"."&INDEX(_xlfn.TEXTSPLIT(I45,"."),3),"")} -> P4.1 | F45: =IFERROR(CONCATENATE(E45,". ",VLOOKUP(E45,'results, prods y acts'!$G$2:$H$16,2,FALSE)),"") -> P4.1. Estrategia para la eficiencia de procesos | G45: A nivel GSN | I45: R1.P4.1.2 | J45: Seguimiento a la validación de TI en la gestión | K45: =CONCATENATE(I45,". ",J45) -> R1.P4.1.2. Seguimiento a la validación de TI en la gestión | L45: Número de propuesta | M45: Propuesta | N45: Informe | O45: Herramienta validada de evaluación de estado situacional del PP0057 | R45: 1 | AB45: =SUM(P45:AA45) -> 1
A46: R1 | B46: =IFERROR(CONCATENATE(A46,". ",VLOOKUP(A46,'results, prods y acts'!$A$2:$B$8,2,FALSE)),"") -> R1. Los procesos de gestión de gasto corriente vinculados a los servicios básicos priorizados a cargo de los GSN son más eficaces y eficientes | C46: P4 | D46: =IFERROR(CONCATENATE(C46,". ",VLOOKUP(C46,'results, prods y acts'!$D$2:$E$12,2,FALSE)),CONCATENATE(C46,". ")) -> P4. Tecnologia de la Informacion / Instrumentos de innovación | E46: {=IFERROR(INDEX(_xlfn.TEXTSPLIT(I46,"."),2)&"."&INDEX(_xlfn.TEXTSPLIT(I46,"."),3),"")} -> P4.1 | F46: =IFERROR(CONCATENATE(E46,". ",VLOOKUP(E46,'results, prods y acts'!$G$2:$H$16,2,FALSE)),"") -> P4.1. Estrategia para la eficiencia de procesos | G46: A nivel GSN | I46: R1.P4.1.3 | J46: Acompañamiento a la implementacion de TI en la gestion | K46: =CONCATENATE(I46,". ",J46) -> R1.P4.1.3. Acompañamiento a la implementacion de TI en la gestion | L46: Número de propuesta | M46: Propuesta | N46: Informe | O46: Herramienta Implementada en los GSN de evaluación de estado situacional del PP0057 | Y46: 1 | AB46: =SUM(P46:AA46) -> 1
A47: R1 | B47: =IFERROR(CONCATENATE(A47,". ",VLOOKUP(A47,'results, prods y acts'!$A$2:$B$8,2,FALSE)),"") -> R1. Los procesos de gestión de gasto corriente vinculados a los servicios básicos priorizados a cargo de los GSN son más eficaces y eficientes | C47: P5 | D47: =IFERROR(CONCATENATE(C47,". ",VLOOKUP(C47,'results, prods y acts'!$D$2:$E$12,2,FALSE)),CONCATENATE(C47,". ")) -> P5. Instrumentos de Gestión del Conocimiento (Publicaciones) | E47: {=IFERROR(INDEX(_xlfn.TEXTSPLIT(I47,"."),2)&"."&INDEX(_xlfn.TEXTSPLIT(I47,"."),3),"")} -> P5.1 | F47: =IFERROR(CONCATENATE(E47,". ",VLOOKUP(E47,'results, prods y acts'!$G$2:$H$16,2,FALSE)),"") -> P5.1. Documentos de trabajo | G47: A nivel GSN | I47: R1.P5.1.1 | J47: Propuesta de Publicaciones | K47: =CONCATENATE(I47,". ",J47) -> R1.P5.1.1. Propuesta de Publicaciones | L47: Número de propuesta | M47: Documento | N47: Publicacion | O47: GSNs con documentos de lineamientos para la mejora de la gestión de almacén. | U47: 1 | V47: 1 | X47: 1 | Z47: 1 | AB47: =SUM(P47:AA47) -> 4
A48: R1 | B48: =IFERROR(CONCATENATE(A48,". ",VLOOKUP(A48,'results, prods y acts'!$A$2:$B$8,2,FALSE)),"") -> R1. Los procesos de gestión de gasto corriente vinculados a los servicios básicos priorizados a cargo de los GSN son más eficaces y eficientes | C48: P5 | D48: =IFERROR(CONCATENATE(C48,". ",VLOOKUP(C48,'results, prods y acts'!$D$2:$E$12,2,FALSE)),CONCATENATE(C48,". ")) -> P5. Instrumentos de Gestión del Conocimiento (Publicaciones) | E48: {=IFERROR(INDEX(_xlfn.TEXTSPLIT(I48,"."),2)&"."&INDEX(_xlfn.TEXTSPLIT(I48,"."),3),"")} -> P5.3 | F48: =IFERROR(CONCATENATE(E48,". ",VLOOKUP(E48,'results, prods y acts'!$G$2:$H$16,2,FALSE)),"") -> P5.3. Documentos de política | G48: A nivel GSN | I48: R1.P5.3.1 | J48: Recomendaciones sobre la gestión del abastecimiento relacionado con los SBP | K48: =CONCATENATE(I48,". ",J48) -> R1.P5.3.1. Recomendaciones sobre la gestión del abastecimiento relacionado con los SBP | L48: Número de documentos | M48: Documento | N48: Presentación | O48: GSNs con documentos de lineamientos para la mejora de la gestión de abastecimiento. | Q48: 1 | R48: 1 | T48: 3 | V48: 1 | X48: 1 | AA48: 1 | AB48: =SUM(P48:AA48) -> 8
A49: R1 | B49: =IFERROR(CONCATENATE(A49,". ",VLOOKUP(A49,'results, prods y acts'!$A$2:$B$8,2,FALSE)),"") -> R1. Los procesos de gestión de gasto corriente vinculados a los servicios básicos priorizados a cargo de los GSN son más eficaces y eficientes | C49: P5 | D49: =IFERROR(CONCATENATE(C49,". ",VLOOKUP(C49,'results, prods y acts'!$D$2:$E$12,2,FALSE)),CONCATENATE(C49,". ")) -> P5. Instrumentos de Gestión del Conocimiento (Publicaciones) | E49: {=IFERROR(INDEX(_xlfn.TEXTSPLIT(I49,"."),2)&"."&INDEX(_xlfn.TEXTSPLIT(I49,"."),3),"")} -> P5.3 | F49: =IFERROR(CONCATENATE(E49,". ",VLOOKUP(E49,'results, prods y acts'!$G$2:$H$16,2,FALSE)),"") -> P5.3. Documentos de política | G49: A nivel GSN | I49: R1.P5.3.2 | J49: Recomendaciones sobre la gestión del abastecimiento relacionado con las ACR | K49: =CONCATENATE(I49,". ",J49) -> R1.P5.3.2. Recomendaciones sobre la gestión del abastecimiento relacionado con las ACR | L49: Número de documentos | M49: Documento | N49: Presentación | O49: ACR con documentos de lineamientos para la mejora de la gestión de abastecimiento. | Z49: 1 | AB49: =SUM(P49:AA49) -> 1
A50: R1 | B50: =IFERROR(CONCATENATE(A50,". ",VLOOKUP(A50,'results, prods y acts'!$A$2:$B$8,2,FALSE)),"") -> R1. Los procesos de gestión de gasto corriente vinculados a los servicios básicos priorizados a cargo de los GSN son más eficaces y eficientes | C50: P6 | D50: =IFERROR(CONCATENATE(C50,". ",VLOOKUP(C50,'results, prods y acts'!$D$2:$E$12,2,FALSE)),CONCATENATE(C50,". ")) -> P6. | F50: =IFERROR(CONCATENATE(E50,". ",VLOOKUP(E50,'results, prods y acts'!$G$2:$H$16,2,FALSE)),"") | G50: A nivel Nacional | H50: MEF- Dirección General de Abastecimiento-DGA | I50: R1.P6.1.1 | J50: Reuniones de coordinaciones respecto a las nuevas normas, Asistencia técnica a los GSN, comentarios y aportaciones al Sistema Nacional de Abastecimiento y/o herramientas informáticas. | K50: =CONCATENATE(I50,". ",J50) -> R1.P6.1.1. Reuniones de coordinaciones respecto a las nuevas normas, Asistencia técnica a los GSN, comentarios y aportaciones al Sistema Nacional de Abastecimiento y/o herramientas informáticas. | L50: Número de reuniones | M50: Reunión | N50: Informe | O50: Programa apoya a los GSN, presenta comentarios y aportaciones a la DGA. | P50: 1 | Q50: 1 | R50: 1 | S50: 1 | T50: 1 | U50: 1 | AB50: =SUM(P50:AA50) -> 6
A51: R1 | B51: =IFERROR(CONCATENATE(A51,". ",VLOOKUP(A51,'results, prods y acts'!$A$2:$B$8,2,FALSE)),"") -> R1. Los procesos de gestión de gasto corriente vinculados a los servicios básicos priorizados a cargo de los GSN son más eficaces y eficientes | C51: P6 | D51: =IFERROR(CONCATENATE(C51,". ",VLOOKUP(C51,'results, prods y acts'!$D$2:$E$12,2,FALSE)),CONCATENATE(C51,". ")) -> P6. | F51: =IFERROR(CONCATENATE(E51,". ",VLOOKUP(E51,'results, prods y acts'!$G$2:$H$16,2,FALSE)),"") | G51: A nivel Nacional | H51: MEF- Dirección General de Abastecimiento-DGA | I51: R1.P6.1.2 | J51: Reuniones de coordinación articulada con la DGA para realizar capacitaciones relacionadas a las normas legales vigentes en la Ley de Contrataciones del Estado y absoluciones de consultas del GSN | K51: =CONCATENATE(I51,". ",J51) -> R1.P6.1.2. Reuniones de coordinación articulada con la DGA para realizar capacitaciones relacionadas a las normas legales vigentes en la Ley de Contrataciones del Estado y absoluciones de consultas del GSN | L51: Número de reuniones | M51: Reunión | N51: Informe | O51: DGA apoya en el fortalecimiento de capacidades en la Ley de Contrataciones a los GSN | Q51: 1 | R51: 1 | T51: 1 | AB51: =SUM(P51:AA51) -> 3
A52: R1 | B52: =IFERROR(CONCATENATE(A52,". ",VLOOKUP(A52,'results, prods y acts'!$A$2:$B$8,2,FALSE)),"") -> R1. Los procesos de gestión de gasto corriente vinculados a los servicios básicos priorizados a cargo de los GSN son más eficaces y eficientes | C52: P6 | D52: =IFERROR(CONCATENATE(C52,". ",VLOOKUP(C52,'results, prods y acts'!$D$2:$E$12,2,FALSE)),CONCATENATE(C52,". ")) -> P6. | F52: =IFERROR(CONCATENATE(E52,". ",VLOOKUP(E52,'results, prods y acts'!$G$2:$H$16,2,FALSE)),"") | G52: A nivel Nacional | H52: Ministerio de Educación - MINEDU | I52: R1.P6.2.1 | J52: Reuniones de coordinación y apoyo para absolver consultas relacionadas a la programación y distribución oportuna del material educativo, y; distribución de bienes patrimoniales a las IIEE de los GSN. | K52: =CONCATENATE(I52,". ",J52) -> R1.P6.2.1. Reuniones de coordinación y apoyo para absolver consultas relacionadas a la programación y distribución oportuna del material educativo, y; distribución de bienes patrimoniales a las IIEE de los GSN. | L52: Número de reuniones | M52: Reunión | N52: Informe | O52: MINEDU absuelva las consultas oportunamente de los GSN | Q52: 4 | R52: 3 | S52: 2 | U52: 1 | Z52: 1 | AB52: =SUM(P52:AA52) -> 11
A53: R1 | B53: =IFERROR(CONCATENATE(A53,". ",VLOOKUP(A53,'results, prods y acts'!$A$2:$B$8,2,FALSE)),"") -> R1. Los procesos de gestión de gasto corriente vinculados a los servicios básicos priorizados a cargo de los GSN son más eficaces y eficientes | C53: P6 | D53: =IFERROR(CONCATENATE(C53,". ",VLOOKUP(C53,'results, prods y acts'!$D$2:$E$12,2,FALSE)),CONCATENATE(C53,". ")) -> P6. | F53: =IFERROR(CONCATENATE(E53,". ",VLOOKUP(E53,'results, prods y acts'!$G$2:$H$16,2,FALSE)),"") | G53: A nivel Nacional | H53: Ministerio de Salud - MINSA | I53: R1.P6.3.1 | J53: Reuniones de coordinación con MINSA para absolver consultas relacionadas a la programación y distribución oportuna de las vacunas y sulfato ferroso a los GSN | K53: =CONCATENATE(I53,". ",J53) -> R1.P6.3.1. Reuniones de coordinación con MINSA para absolver consultas relacionadas a la programación y distribución oportuna de las vacunas y sulfato ferroso a los GSN | L53: Número de reuniones | M53: Reunión | N53: Informe | O53: CENARES absuelva las consultas oportunamente | S53: 1 | Y53: 1 | AB53: =SUM(P53:AA53) -> 2
A54: R1 | B54: =IFERROR(CONCATENATE(A54,". ",VLOOKUP(A54,'results, prods y acts'!$A$2:$B$8,2,FALSE)),"") -> R1. Los procesos de gestión de gasto corriente vinculados a los servicios básicos priorizados a cargo de los GSN son más eficaces y eficientes | C54: P6 | D54: =IFERROR(CONCATENATE(C54,". ",VLOOKUP(C54,'results, prods y acts'!$D$2:$E$12,2,FALSE)),CONCATENATE(C54,". ")) -> P6. | F54: =IFERROR(CONCATENATE(E54,". ",VLOOKUP(E54,'results, prods y acts'!$G$2:$H$16,2,FALSE)),"") | G54: A nivel Nacional | H54: Centro Nacional de Planeamiento Estratégico - CEPLAN | I54: R1.P6.4.1 | J54: Reuniones de trabajo para promover la articulación de la planificación operativa y la programación de la demanda de bienes y servicios relacionados con los servicios básicos priorizados y fortalecimiento de capacidades a los GSN. Coordinación de atención de consultas de los GSN. | K54: =CONCATENATE(I54,". ",J54) -> R1.P6.4.1. Reuniones de trabajo para promover la articulación de la planificación operativa y la programación de la demanda de bienes y servicios relacionados con los servicios básicos priorizados y fortalecimiento de capacidades a los GSN. Coordinación de atención de consultas de los GSN. | L54: Número de reuniones | M54: Reunión | N54: Informe | O54: Ceplan fortalece el proceso de articulación de la planificación con la programación de bienes y servicios. | Q54: 1 | S54: 1 | AB54: =SUM(P54:AA54) -> 2
A55: R2 | B55: =IFERROR(CONCATENATE(A55,". ",VLOOKUP(A55,'results, prods y acts'!$A$2:$B$8,2,FALSE)),"") -> R2. Los procesos de gestión de gasto de capital vinculados a los servicios priorizados a cargo de los GSN son más eficaces y eficientes | C55: P1 | D55: =IFERROR(CONCATENATE(C55,". ",VLOOKUP(C55,'results, prods y acts'!$D$2:$E$12,2,FALSE)),CONCATENATE(C55,". ")) -> P1. Asistencia técnica | E55: {=IFERROR(INDEX(_xlfn.TEXTSPLIT(I55,"."),2)&"."&INDEX(_xlfn.TEXTSPLIT(I55,"."),3),"")} -> P1.2 | F55: =IFERROR(CONCATENATE(E55,". ",VLOOKUP(E55,'results, prods y acts'!$G$2:$H$16,2,FALSE)),"") -> P1.2. Acompañamiento | G55: A nivel GSN | I55: R2.P1.2.2 | J55: Acompañamiento de los proyectos de inversión, gestionado desde el gobierno nacional de interés regional. | K55: =CONCATENATE(I55,". ",J55) -> R2.P1.2.2. Acompañamiento de los proyectos de inversión, gestionado desde el gobierno nacional de interés regional. | L55: Número de acompañamientos | M55: Acompañamiento | N55: Ficha de Seguimiento | O55: GSN en capacidad de hacer seguimiento a proyectos de su interés | R55: 1 | U55: 1 | X55: 1 | AA55: 1 | AB55: =SUM(P55:AA55) -> 4
A56: R2 | B56: =IFERROR(CONCATENATE(A56,". ",VLOOKUP(A56,'results, prods y acts'!$A$2:$B$8,2,FALSE)),"") -> R2. Los procesos de gestión de gasto de capital vinculados a los servicios priorizados a cargo de los GSN son más eficaces y eficientes | C56: P1 | D56: =IFERROR(CONCATENATE(C56,". ",VLOOKUP(C56,'results, prods y acts'!$D$2:$E$12,2,FALSE)),CONCATENATE(C56,". ")) -> P1. Asistencia técnica | E56: {=IFERROR(INDEX(_xlfn.TEXTSPLIT(I56,"."),2)&"."&INDEX(_xlfn.TEXTSPLIT(I56,"."),3),"")} -> P1.2 | F56: =IFERROR(CONCATENATE(E56,". ",VLOOKUP(E56,'results, prods y acts'!$G$2:$H$16,2,FALSE)),"") -> P1.2. Acompañamiento | G56: A nivel GSN | I56: R2.P1.2.3 | J56: Acompañamiento en la fase de Programación Multianual de Inversiones, y en particular de la cartera priorizada con el GSN. | K56: =CONCATENATE(I56,". ",J56) -> R2.P1.2.3. Acompañamiento en la fase de Programación Multianual de Inversiones, y en particular de la cartera priorizada con el GSN. | L56: Número de acompañamientos | M56: Acompañamiento | N56: Ficha de Seguimiento | O56: GSN realizan una adecuada Programación Multianual de Inversiones | R56: 11 | AB56: =SUM(P56:AA56) -> 11
A57: R2 | B57: =IFERROR(CONCATENATE(A57,". ",VLOOKUP(A57,'results, prods y acts'!$A$2:$B$8,2,FALSE)),"") -> R2. Los procesos de gestión de gasto de capital vinculados a los servicios priorizados a cargo de los GSN son más eficaces y eficientes | C57: P1 | D57: =IFERROR(CONCATENATE(C57,". ",VLOOKUP(C57,'results, prods y acts'!$D$2:$E$12,2,FALSE)),CONCATENATE(C57,". ")) -> P1. Asistencia técnica | E57: {=IFERROR(INDEX(_xlfn.TEXTSPLIT(I57,"."),2)&"."&INDEX(_xlfn.TEXTSPLIT(I57,"."),3),"")} -> P1.2 | F57: =IFERROR(CONCATENATE(E57,". ",VLOOKUP(E57,'results, prods y acts'!$G$2:$H$16,2,FALSE)),"") -> P1.2. Acompañamiento | G57: A nivel GSN | I57: R2.P1.2.4 | J57: Acompañamiento en la consistencia del PMI 2025 con el PIA 2026 del GSN. | K57: =CONCATENATE(I57,". ",J57) -> R2.P1.2.4. Acompañamiento en la consistencia del PMI 2025 con el PIA 2026 del GSN. | L57: Número de acompañamientos | M57: GSN | N57: Ficha de Seguimiento | O57: GSN realizan su programación multianual de acuerdo a la normatividad vigente | Y57: 11 | AB57: =SUM(P57:AA57) -> 11
A58: R2 | B58: =IFERROR(CONCATENATE(A58,". ",VLOOKUP(A58,'results, prods y acts'!$A$2:$B$8,2,FALSE)),"") -> R2. Los procesos de gestión de gasto de capital vinculados a los servicios priorizados a cargo de los GSN son más eficaces y eficientes | C58: P1 | D58: =IFERROR(CONCATENATE(C58,". ",VLOOKUP(C58,'results, prods y acts'!$D$2:$E$12,2,FALSE)),CONCATENATE(C58,". ")) -> P1. Asistencia técnica | E58: {=IFERROR(INDEX(_xlfn.TEXTSPLIT(I58,"."),2)&"."&INDEX(_xlfn.TEXTSPLIT(I58,"."),3),"")} -> P1.2 | F58: =IFERROR(CONCATENATE(E58,". ",VLOOKUP(E58,'results, prods y acts'!$G$2:$H$16,2,FALSE)),"") -> P1.2. Acompañamiento | G58: A nivel GSN | I58: R2.P1.2.5 | J58: Acompañamiento en la fase de Formulación y Evaluación de Inversiones, y en particular de la cartera priorizada con el GSN. | K58: =CONCATENATE(I58,". ",J58) -> R2.P1.2.5. Acompañamiento en la fase de Formulación y Evaluación de Inversiones, y en particular de la cartera priorizada con el GSN. | L58: Número de acompañamientos | M58: Acompañamiento | N58: Ficha de Seguimiento | O58: GSN formulan y aprueban sus proyectos de acuerdo a la normatividad vigente | U58: 2 | AA58: 2 | AB58: =SUM(P58:AA58) -> 4
A59: R2 | B59: =IFERROR(CONCATENATE(A59,". ",VLOOKUP(A59,'results, prods y acts'!$A$2:$B$8,2,FALSE)),"") -> R2. Los procesos de gestión de gasto de capital vinculados a los servicios priorizados a cargo de los GSN son más eficaces y eficientes | C59: P1 | D59: =IFERROR(CONCATENATE(C59,". ",VLOOKUP(C59,'results, prods y acts'!$D$2:$E$12,2,FALSE)),CONCATENATE(C59,". ")) -> P1. Asistencia técnica | E59: {=IFERROR(INDEX(_xlfn.TEXTSPLIT(I59,"."),2)&"."&INDEX(_xlfn.TEXTSPLIT(I59,"."),3),"")} -> P1.2 | F59: =IFERROR(CONCATENATE(E59,". ",VLOOKUP(E59,'results, prods y acts'!$G$2:$H$16,2,FALSE)),"") -> P1.2. Acompañamiento | G59: A nivel GSN | I59: R2.P1.2.6 | J59: Acompañamiento en la fase de Ejecución de Inversiones, y en particular de la cartera priorizada con el GSN. | K59: =CONCATENATE(I59,". ",J59) -> R2.P1.2.6. Acompañamiento en la fase de Ejecución de Inversiones, y en particular de la cartera priorizada con el GSN. | L59: Número de acompañamientos | M59: GSN | N59: Ficha de Seguimiento | O59: GSN ejecutan sus inversiones con la oportunidad y calidad requerida | R59: 11 | U59: 11 | X59: 11 | AA59: 11 | AB59: =SUM(P59:AA59) -> 44
A60: R2 | B60: =IFERROR(CONCATENATE(A60,". ",VLOOKUP(A60,'results, prods y acts'!$A$2:$B$8,2,FALSE)),"") -> R2. Los procesos de gestión de gasto de capital vinculados a los servicios priorizados a cargo de los GSN son más eficaces y eficientes | C60: P1 | D60: =IFERROR(CONCATENATE(C60,". ",VLOOKUP(C60,'results, prods y acts'!$D$2:$E$12,2,FALSE)),CONCATENATE(C60,". ")) -> P1. Asistencia técnica | E60: {=IFERROR(INDEX(_xlfn.TEXTSPLIT(I60,"."),2)&"."&INDEX(_xlfn.TEXTSPLIT(I60,"."),3),"")} -> P1.2 | F60: =IFERROR(CONCATENATE(E60,". ",VLOOKUP(E60,'results, prods y acts'!$G$2:$H$16,2,FALSE)),"") -> P1.2. Acompañamiento | G60: A nivel GSN | I60: R2.P1.2.7 | J60: Acompañamiento para la verificación de avance físico de la ejecución de inversiones de la cartera priorizada con el GSN. | K60: =CONCATENATE(I60,". ",J60) -> R2.P1.2.7. Acompañamiento para la verificación de avance físico de la ejecución de inversiones de la cartera priorizada con el GSN. | L60: Número de acompañamientos | M60: Visita | N60: Ficha de Seguimiento | O60: Se verifica el avance de las obras de las carteras priorizadas con los GSN según la programación | U60: 35 | AA60: 40 | AB60: =SUM(P60:AA60) -> 75
A61: R2 | B61: =IFERROR(CONCATENATE(A61,". ",VLOOKUP(A61,'results, prods y acts'!$A$2:$B$8,2,FALSE)),"") -> R2. Los procesos de gestión de gasto de capital vinculados a los servicios priorizados a cargo de los GSN son más eficaces y eficientes | C61: P1 | D61: =IFERROR(CONCATENATE(C61,". ",VLOOKUP(C61,'results, prods y acts'!$D$2:$E$12,2,FALSE)),CONCATENATE(C61,". ")) -> P1. Asistencia técnica | E61: {=IFERROR(INDEX(_xlfn.TEXTSPLIT(I61,"."),2)&"."&INDEX(_xlfn.TEXTSPLIT(I61,"."),3),"")} -> P1.2 | F61: =IFERROR(CONCATENATE(E61,". ",VLOOKUP(E61,'results, prods y acts'!$G$2:$H$16,2,FALSE)),"") -> P1.2. Acompañamiento | G61: A nivel GSN | I61: R2.P1.2.8 | J61: Acompañamiento para la verificación del funcionamiento de las inversiones concluidas de la cartera priorizada con el GSN | K61: =CONCATENATE(I61,". ",J61) -> R2.P1.2.8. Acompañamiento para la verificación del funcionamiento de las inversiones concluidas de la cartera priorizada con el GSN | L61: Número de acompañamientos | M61: Visita | N61: Ficha de Seguimiento | O61: Obras concluidas son entregadas a los operadores del servicio | Q61: 1 | S61: 1 | U61: 1 | W61: 2 | Y61: 2 | AB61: =SUM(P61:AA61) -> 7
A62: R2 | B62: =IFERROR(CONCATENATE(A62,". ",VLOOKUP(A62,'results, prods y acts'!$A$2:$B$8,2,FALSE)),"") -> R2. Los procesos de gestión de gasto de capital vinculados a los servicios priorizados a cargo de los GSN son más eficaces y eficientes | C62: P1 | D62: =IFERROR(CONCATENATE(C62,". ",VLOOKUP(C62,'results, prods y acts'!$D$2:$E$12,2,FALSE)),CONCATENATE(C62,". ")) -> P1. Asistencia técnica | E62: {=IFERROR(INDEX(_xlfn.TEXTSPLIT(I62,"."),2)&"."&INDEX(_xlfn.TEXTSPLIT(I62,"."),3),"")} -> P1.3 | F62: =IFERROR(CONCATENATE(E62,". ",VLOOKUP(E62,'results, prods y acts'!$G$2:$H$16,2,FALSE)),"") -> P1.3. Reuniones de retroalimentación | G62: A nivel GSN | I62: R2.P1.3.1 | J62: Reuniones retroalimentación para el seguimiento de la Ejecución de la cartera de inversiones que maneja el GSN, y en particular de la cartera priorizada con el GSN. | K62: =CONCATENATE(I62,". ",J62) -> R2.P1.3.1. Reuniones retroalimentación para el seguimiento de la Ejecución de la cartera de inversiones que maneja el GSN, y en particular de la cartera priorizada con el GSN. | L62: Número de reuniones de retroalimentación | M62: Reunión | N62: Ficha de Seguimiento | O62: GSN fortalecen su gestión de ejecución de inversiones | R62: 11 | U62: 11 | X62: 11 | AA62: 11 | AB62: =SUM(P62:AA62) -> 44
A63: R2 | B63: =IFERROR(CONCATENATE(A63,". ",VLOOKUP(A63,'results, prods y acts'!$A$2:$B$8,2,FALSE)),"") -> R2. Los procesos de gestión de gasto de capital vinculados a los servicios priorizados a cargo de los GSN son más eficaces y eficientes | C63: P2 | D63: =IFERROR(CONCATENATE(C63,". ",VLOOKUP(C63,'results, prods y acts'!$D$2:$E$12,2,FALSE)),CONCATENATE(C63,". ")) -> P2. Fortalecimiento de capacidades | E63: {=IFERROR(INDEX(_xlfn.TEXTSPLIT(I63,"."),2)&"."&INDEX(_xlfn.TEXTSPLIT(I63,"."),3),"")} -> P2.1 | F63: =IFERROR(CONCATENATE(E63,". ",VLOOKUP(E63,'results, prods y acts'!$G$2:$H$16,2,FALSE)),"") -> P2.1. Cursos | G63: A nivel GSN | I63: R2.P2.1.1 | J63: Curso relacionados a la gestión de inversiones (incluye presencial en regiones) | K63: =CONCATENATE(I63,". ",J63) -> R2.P2.1.1. Curso relacionados a la gestión de inversiones (incluye presencial en regiones) | L63: Número de cursos | M63: Curso | N63: Informe y Actas | O63: Personal de los GSN son capacitados | R63: 1 | S63: 1 | T63: 1 | AB63: =SUM(P63:AA63) -> 3
A64: R2 | B64: =IFERROR(CONCATENATE(A64,". ",VLOOKUP(A64,'results, prods y acts'!$A$2:$B$8,2,FALSE)),"") -> R2. Los procesos de gestión de gasto de capital vinculados a los servicios priorizados a cargo de los GSN son más eficaces y eficientes | C64: P2 | D64: =IFERROR(CONCATENATE(C64,". ",VLOOKUP(C64,'results, prods y acts'!$D$2:$E$12,2,FALSE)),CONCATENATE(C64,". ")) -> P2. Fortalecimiento de capacidades | E64: {=IFERROR(INDEX(_xlfn.TEXTSPLIT(I64,"."),2)&"."&INDEX(_xlfn.TEXTSPLIT(I64,"."),3),"")} -> P2.5 | F64: =IFERROR(CONCATENATE(E64,". ",VLOOKUP(E64,'results, prods y acts'!$G$2:$H$16,2,FALSE)),"") -> P2.5. Charla | G64: A nivel GSN | I64: R2.P2.5.1 | J64: Charlas sobre normatividad sectorial, y/o diversos items vinvulados a la gestion de inversiones. | K64: =CONCATENATE(I64,". ",J64) -> R2.P2.5.1. Charlas sobre normatividad sectorial, y/o diversos items vinvulados a la gestion de inversiones. | L64: Número de Charlas | M64: Charla | N64: Informe y Actas | O64: Los GSN mejoran sus procesos de gestión de inversiones | S64: 1 | T64: 2 | U64: 2 | V64: 2 | W64: 2 | X64: 2 | Y64: 2 | Z64: 2 | AA64: 2 | AB64: =SUM(P64:AA64) -> 17
A65: R2 | B65: =IFERROR(CONCATENATE(A65,". ",VLOOKUP(A65,'results, prods y acts'!$A$2:$B$8,2,FALSE)),"") -> R2. Los procesos de gestión de gasto de capital vinculados a los servicios priorizados a cargo de los GSN son más eficaces y eficientes | C65: P3 | D65: =IFERROR(CONCATENATE(C65,". ",VLOOKUP(C65,'results, prods y acts'!$D$2:$E$12,2,FALSE)),CONCATENATE(C65,". ")) -> P3. Instrumentos de mejora de la gestión | E65: {=IFERROR(INDEX(_xlfn.TEXTSPLIT(I65,"."),2)&"."&INDEX(_xlfn.TEXTSPLIT(I65,"."),3),"")} -> P3.4 | F65: =IFERROR(CONCATENATE(E65,". ",VLOOKUP(E65,'results, prods y acts'!$G$2:$H$16,2,FALSE)),"") -> P3.4. Propuesta de modificación técnico-administrativa a nivel institucional | G65: A nivel GSN | I65: R2.P3.4.1 | J65: Acompañamiento en desarrollo de instrumentos de gestión relacionadas con las inversiones | K65: =CONCATENATE(I65,". ",J65) -> R2.P3.4.1. Acompañamiento en desarrollo de instrumentos de gestión relacionadas con las inversiones | L65: Número de acompañamientos | M65: Acompañamiento | N65: Ficha de Seguimiento | O65: GSN tienen una gestión más ordenada y transparente | S65: 1 | AB65: =SUM(P65:AA65) -> 1
A66: R2 | B66: =IFERROR(CONCATENATE(A66,". ",VLOOKUP(A66,'results, prods y acts'!$A$2:$B$8,2,FALSE)),"") -> R2. Los procesos de gestión de gasto de capital vinculados a los servicios priorizados a cargo de los GSN son más eficaces y eficientes | C66: P3 | D66: =IFERROR(CONCATENATE(C66,". ",VLOOKUP(C66,'results, prods y acts'!$D$2:$E$12,2,FALSE)),CONCATENATE(C66,". ")) -> P3. Instrumentos de mejora de la gestión | E66: {=IFERROR(INDEX(_xlfn.TEXTSPLIT(I66,"."),2)&"."&INDEX(_xlfn.TEXTSPLIT(I66,"."),3),"")} -> P3.5 | F66: =IFERROR(CONCATENATE(E66,". ",VLOOKUP(E66,'results, prods y acts'!$G$2:$H$16,2,FALSE)),"") -> P3.5. Propuesta de modificación técnico-administrativa a nivel sectorial | G66: A nivel GSN | I66: R2.P3.5.1 | J66: Propuesta de reforma técnico administrativa a nivel sectorial | K66: =CONCATENATE(I66,". ",J66) -> R2.P3.5.1 . Propuesta de reforma técnico administrativa a nivel sectorial | L66: Número de propuestas | M66: Propuesta | N66: Informe | O66: GSN tienen una gestión más ordenada y transparente | U66: 1 | AB66: =SUM(P66:AA66) -> 1
A67: R2 | B67: =IFERROR(CONCATENATE(A67,". ",VLOOKUP(A67,'results, prods y acts'!$A$2:$B$8,2,FALSE)),"") -> R2. Los procesos de gestión de gasto de capital vinculados a los servicios priorizados a cargo de los GSN son más eficaces y eficientes | C67: P4 | D67: =IFERROR(CONCATENATE(C67,". ",VLOOKUP(C67,'results, prods y acts'!$D$2:$E$12,2,FALSE)),CONCATENATE(C67,". ")) -> P4. Tecnologia de la Informacion / Instrumentos de innovación | E67: {=IFERROR(INDEX(_xlfn.TEXTSPLIT(I67,"."),2)&"."&INDEX(_xlfn.TEXTSPLIT(I67,"."),3),"")} -> P4.1 | F67: =IFERROR(CONCATENATE(E67,". ",VLOOKUP(E67,'results, prods y acts'!$G$2:$H$16,2,FALSE)),"") -> P4.1. Estrategia para la eficiencia de procesos | G67: A nivel GSN | I67: R2.P4.1.1 | J67: Propuesta de Eficiencia de procesos | K67: =CONCATENATE(I67,". ",J67) -> R2.P4.1.1. Propuesta de Eficiencia de procesos | L67: Número de propuestas | M67: Propuesta | N67: Informe | O67: GSN tienen una gestión más ordenada y transparente | Z67: 1 | AB67: =SUM(P67:AA67) -> 1
A68: R2 | B68: =IFERROR(CONCATENATE(A68,". ",VLOOKUP(A68,'results, prods y acts'!$A$2:$B$8,2,FALSE)),"") -> R2. Los procesos de gestión de gasto de capital vinculados a los servicios priorizados a cargo de los GSN son más eficaces y eficientes | C68: P4 | D68: =IFERROR(CONCATENATE(C68,". ",VLOOKUP(C68,'results, prods y acts'!$D$2:$E$12,2,FALSE)),CONCATENATE(C68,". ")) -> P4. Tecnologia de la Informacion / Instrumentos de innovación | E68: {=IFERROR(INDEX(_xlfn.TEXTSPLIT(I68,"."),2)&"."&INDEX(_xlfn.TEXTSPLIT(I68,"."),3),"")} -> P4.2 | F68: =IFERROR(CONCATENATE(E68,". ",VLOOKUP(E68,'results, prods y acts'!$G$2:$H$16,2,FALSE)),"") -> P4.2. Intervención costo-efectivaaa | G68: A nivel GSN | I68: R2.P4.2.1 | J68: Propuesta de Intervención costo-efectiva | K68: =CONCATENATE(I68,". ",J68) -> R2.P4.2.1. Propuesta de Intervención costo-efectiva | L68: Número de propuestas | M68: Propuesta | N68: Informe | O68: GSN tienen una gestión más ordenada y transparente | U68: 1 | AB68: =SUM(P68:AA68) -> 1
A69: R2 | B69: =IFERROR(CONCATENATE(A69,". ",VLOOKUP(A69,'results, prods y acts'!$A$2:$B$8,2,FALSE)),"") -> R2. Los procesos de gestión de gasto de capital vinculados a los servicios priorizados a cargo de los GSN son más eficaces y eficientes | C69: P5 | D69: =IFERROR(CONCATENATE(C69,". ",VLOOKUP(C69,'results, prods y acts'!$D$2:$E$12,2,FALSE)),CONCATENATE(C69,". ")) -> P5. Instrumentos de Gestión del Conocimiento (Publicaciones) | E69: {=IFERROR(INDEX(_xlfn.TEXTSPLIT(I69,"."),2)&"."&INDEX(_xlfn.TEXTSPLIT(I69,"."),3),"")} -> P5.2 | F69: =IFERROR(CONCATENATE(E69,". ",VLOOKUP(E69,'results, prods y acts'!$G$2:$H$16,2,FALSE)),"") -> P5.2. Documentos de buenas prácticas y lecciones aprendidas | G69: A nivel GSN | I69: R2.P5.2.1 | J69: Documentos de buenas prácticas | K69: =CONCATENATE(I69,". ",J69) -> R2.P5.2.1. Documentos de buenas prácticas | L69: Número de documentos | M69: Documento | N69: Documento | O69: Difusión de buenas prácticas implementadas en los GSN | AA69: 1 | AB69: =SUM(P69:AA69) -> 1
A70: R2 | B70: =IFERROR(CONCATENATE(A70,". ",VLOOKUP(A70,'results, prods y acts'!$A$2:$B$8,2,FALSE)),"") -> R2. Los procesos de gestión de gasto de capital vinculados a los servicios priorizados a cargo de los GSN son más eficaces y eficientes | C70: P5 | D70: =IFERROR(CONCATENATE(C70,". ",VLOOKUP(C70,'results, prods y acts'!$D$2:$E$12,2,FALSE)),CONCATENATE(C70,". ")) -> P5. Instrumentos de Gestión del Conocimiento (Publicaciones) | E70: {=IFERROR(INDEX(_xlfn.TEXTSPLIT(I70,"."),2)&"."&INDEX(_xlfn.TEXTSPLIT(I70,"."),3),"")} -> P5.3 | F70: =IFERROR(CONCATENATE(E70,". ",VLOOKUP(E70,'results, prods y acts'!$G$2:$H$16,2,FALSE)),"") -> P5.3. Documentos de política | G70: A nivel GSN | I70: R2.P5.3.1 | J70: Documento de politica | K70: =CONCATENATE(I70,". ",J70) -> R2.P5.3.1. Documento de politica | L70: Número de documentos | M70: Documento | N70: Documento/Presentación | O70: GSN tienen una gestión más ordenada y transparente | R70: 1 | T70: 1 | AB70: =SUM(P70:AA70) -> 2
A71: R2 | B71: =IFERROR(CONCATENATE(A71,". ",VLOOKUP(A71,'results, prods y acts'!$A$2:$B$8,2,FALSE)),"") -> R2. Los procesos de gestión de gasto de capital vinculados a los servicios priorizados a cargo de los GSN son más eficaces y eficientes | D71: =IFERROR(CONCATENATE(C71,". ",VLOOKUP(C71,'results, prods y acts'!$D$2:$E$12,2,FALSE)),CONCATENATE(C71,". ")) -> . | F71: =IFERROR(CONCATENATE(E71,". ",VLOOKUP(E71,'results, prods y acts'!$G$2:$H$16,2,FALSE)),"") | G71: A nivel nacional | H71: MEF - Dirección General de Programación Multianual de Inversiones - DGPMI | I71: R2.P6.1.1 | J71: Reuniones de coordinación y compartir información relevante que permita optimizar la ejecución de las inversiones de los GSN. | K71: =CONCATENATE(I71,". ",J71) -> R2.P6.1.1. Reuniones de coordinación y compartir información relevante que permita optimizar la ejecución de las inversiones de los GSN. | L71: Número de reuniones | M71: Reunión | N71: Acta de reunión | O71: Se logran sinergias en el trabajo de asistencia técnica a los GSN | R71: 3 | U71: 3 | X71: 3 | AA71: 4 | AB71: =SUM(P71:AA71) -> 13
A72: R2 | B72: =IFERROR(CONCATENATE(A72,". ",VLOOKUP(A72,'results, prods y acts'!$A$2:$B$8,2,FALSE)),"") -> R2. Los procesos de gestión de gasto de capital vinculados a los servicios priorizados a cargo de los GSN son más eficaces y eficientes | D72: =IFERROR(CONCATENATE(C72,". ",VLOOKUP(C72,'results, prods y acts'!$D$2:$E$12,2,FALSE)),CONCATENATE(C72,". ")) -> . | F72: =IFERROR(CONCATENATE(E72,". ",VLOOKUP(E72,'results, prods y acts'!$G$2:$H$16,2,FALSE)),"") | G72: A nivel nacional | H72: MEF - Dirección General de Programación Multianual de Inversiones - DGPMI | I72: R2.P6.1.2 | J72: Reuniones de coordinación respecto a modificaciones normativas y disposiciones en relación a la ejecución de inversiones de servicios priorizados y la reactivación de obras públicas. | K72: =CONCATENATE(I72,". ",J72) -> R2.P6.1.2. Reuniones de coordinación respecto a modificaciones normativas y disposiciones en relación a la ejecución de inversiones de servicios priorizados y la reactivación de obras públicas. | L72: Número de reuniones | M72: Reunión | N72: Acta de reunión | O72: Conocimiento actualizado de las políticas que maneja el sector nacional en materia de inversiones | U72: 1 | AA72: 1 | AB72: =SUM(P72:AA72) -> 2
A73: R3 | B73: =IFERROR(CONCATENATE(A73,". ",VLOOKUP(A73,'results, prods y acts'!$A$2:$B$8,2,FALSE)),"") -> R3. Los procesos priorizados de recaudación del impuesto predial en los Gobiernos Locales son más eficaces y eficientes | C73: P1 | D73: =IFERROR(CONCATENATE(C73,". ",VLOOKUP(C73,'results, prods y acts'!$D$2:$E$12,2,FALSE)),CONCATENATE(C73,". ")) -> P1. Asistencia técnica | E73: {=IFERROR(INDEX(_xlfn.TEXTSPLIT(I73,"."),2)&"."&INDEX(_xlfn.TEXTSPLIT(I73,"."),3),"")} -> P1.2 | F73: =IFERROR(CONCATENATE(E73,". ",VLOOKUP(E73,'results, prods y acts'!$G$2:$H$16,2,FALSE)),"") -> P1.2. Acompañamiento | G73: A nivel GSN | I73: R3.P1.2.1 | J73: Acompañamiento para la revisión y evaluación de procesos internos de registro, fiscalización y cobranza tributaria municipal | K73: =CONCATENATE(I73,". ",J73) -> R3.P1.2.1. Acompañamiento para la revisión y evaluación de procesos internos de registro, fiscalización y cobranza tributaria municipal | L73: Número de acompañamientos | M73: Acompañamiento | N73: Ficha de Seguimiento | O73: MPs con procesos internos identificados. | R73: 5 | U73: 6 | X73: 5 | AA73: 5 | AB73: =SUM(P73:AA73) -> 21
A74: R3 | B74: =IFERROR(CONCATENATE(A74,". ",VLOOKUP(A74,'results, prods y acts'!$A$2:$B$8,2,FALSE)),"") -> R3. Los procesos priorizados de recaudación del impuesto predial en los Gobiernos Locales son más eficaces y eficientes | C74: P1 | D74: =IFERROR(CONCATENATE(C74,". ",VLOOKUP(C74,'results, prods y acts'!$D$2:$E$12,2,FALSE)),CONCATENATE(C74,". ")) -> P1. Asistencia técnica | E74: {=IFERROR(INDEX(_xlfn.TEXTSPLIT(I74,"."),2)&"."&INDEX(_xlfn.TEXTSPLIT(I74,"."),3),"")} -> P1.2 | F74: =IFERROR(CONCATENATE(E74,". ",VLOOKUP(E74,'results, prods y acts'!$G$2:$H$16,2,FALSE)),"") -> P1.2. Acompañamiento | G74: A nivel GSN | I74: R3.P1.2.2 | J74: Acompañamiento en los procesos y/o actividades que promuevan la ampliación de la base tributaria predial. | K74: =CONCATENATE(I74,". ",J74) -> R3.P1.2.2. Acompañamiento en los procesos y/o actividades que promuevan la ampliación de la base tributaria predial. | L74: Número de acompañamientos | M74: MPs | N74: Ficha de Seguimiento | O74: MPs con un proceso y/o actividad promovida para ampliar base tributaria predial | W74: 5 | AB74: =SUM(P74:AA74) -> 5
A75: R3 | B75: =IFERROR(CONCATENATE(A75,". ",VLOOKUP(A75,'results, prods y acts'!$A$2:$B$8,2,FALSE)),"") -> R3. Los procesos priorizados de recaudación del impuesto predial en los Gobiernos Locales son más eficaces y eficientes | C75: P1 | D75: =IFERROR(CONCATENATE(C75,". ",VLOOKUP(C75,'results, prods y acts'!$D$2:$E$12,2,FALSE)),CONCATENATE(C75,". ")) -> P1. Asistencia técnica | E75: {=IFERROR(INDEX(_xlfn.TEXTSPLIT(I75,"."),2)&"."&INDEX(_xlfn.TEXTSPLIT(I75,"."),3),"")} -> P1.2 | F75: =IFERROR(CONCATENATE(E75,". ",VLOOKUP(E75,'results, prods y acts'!$G$2:$H$16,2,FALSE)),"") -> P1.2. Acompañamiento | G75: A nivel GSN | I75: R3.P1.2.3 | J75: Acompañamiento en programas y actividades promovidas por el MEF, dirigidas a mejorar la recaudación tributaria, implementación y capacitación de uso del nuevo Sistema de Recaudación Tributaria Municipal (SRTM) y el Programa de Apoyo Presupuestario. | K75: =CONCATENATE(I75,". ",J75) -> R3.P1.2.3. Acompañamiento en programas y actividades promovidas por el MEF, dirigidas a mejorar la recaudación tributaria, implementación y capacitación de uso del nuevo Sistema de Recaudación Tributaria Municipal (SRTM) y el Programa de Apoyo Presupuestario. | L75: Número de acompañamientos | M75: Acompañamiento | N75: Ficha de Seguimiento | O75: MPs con programas / actividades promovidas por el MEF para mejora de recaudación y con personal con conocimiento y capacitación sobre nuevo SRTM. | T75: 3 | Y75: 1 | AB75: =SUM(P75:AA75) -> 4
A76: R3 | B76: =IFERROR(CONCATENATE(A76,". ",VLOOKUP(A76,'results, prods y acts'!$A$2:$B$8,2,FALSE)),"") -> R3. Los procesos priorizados de recaudación del impuesto predial en los Gobiernos Locales son más eficaces y eficientes | C76: P1 | D76: =IFERROR(CONCATENATE(C76,". ",VLOOKUP(C76,'results, prods y acts'!$D$2:$E$12,2,FALSE)),CONCATENATE(C76,". ")) -> P1. Asistencia técnica | E76: {=IFERROR(INDEX(_xlfn.TEXTSPLIT(I76,"."),2)&"."&INDEX(_xlfn.TEXTSPLIT(I76,"."),3),"")} -> P1.2 | F76: =IFERROR(CONCATENATE(E76,". ",VLOOKUP(E76,'results, prods y acts'!$G$2:$H$16,2,FALSE)),"") -> P1.2. Acompañamiento | G76: A nivel GSN | I76: R3.P1.2.5 | J76: Acompañamiento en la evaluación y propuestas de mejora de los sistemas informáticos de la administración tributaria, así como su vinculación con el catastro. | K76: =CONCATENATE(I76,". ",J76) -> R3.P1.2.5. Acompañamiento en la evaluación y propuestas de mejora de los sistemas informáticos de la administración tributaria, así como su vinculación con el catastro. | L76: Número de acompañamientos | M76: Acompañamiento | N76: Ficha de Seguimiento | O76: MPs cuentan con sistemas informáticos tributarios con mayores y/o mejores opciones (una evaluación anual) | V76: 5 | AB76: =SUM(P76:AA76) -> 5
A77: R3 | B77: =IFERROR(CONCATENATE(A77,". ",VLOOKUP(A77,'results, prods y acts'!$A$2:$B$8,2,FALSE)),"") -> R3. Los procesos priorizados de recaudación del impuesto predial en los Gobiernos Locales son más eficaces y eficientes | C77: P1 | D77: =IFERROR(CONCATENATE(C77,". ",VLOOKUP(C77,'results, prods y acts'!$D$2:$E$12,2,FALSE)),CONCATENATE(C77,". ")) -> P1. Asistencia técnica | E77: {=IFERROR(INDEX(_xlfn.TEXTSPLIT(I77,"."),2)&"."&INDEX(_xlfn.TEXTSPLIT(I77,"."),3),"")} -> P1.2 | F77: =IFERROR(CONCATENATE(E77,". ",VLOOKUP(E77,'results, prods y acts'!$G$2:$H$16,2,FALSE)),"") -> P1.2. Acompañamiento | G77: A nivel GSN | I77: R3.P1.2.6 | J77: Acompañamiento orientado a la implementación de un proceso oportuno de emisión predial anual | K77: =CONCATENATE(I77,". ",J77) -> R3.P1.2.6. Acompañamiento orientado a la implementación de un proceso oportuno de emisión predial anual | L77: Número de acompañamientos | M77: Acompañamiento | N77: Ficha de Seguimiento | O77: MPs gestionan para implementar una emisión oportuna de tributos (1 anual) | AA77: 6 | AB77: =SUM(P77:AA77) -> 6
A78: R3 | B78: =IFERROR(CONCATENATE(A78,". ",VLOOKUP(A78,'results, prods y acts'!$A$2:$B$8,2,FALSE)),"") -> R3. Los procesos priorizados de recaudación del impuesto predial en los Gobiernos Locales son más eficaces y eficientes | C78: P1 | D78: =IFERROR(CONCATENATE(C78,". ",VLOOKUP(C78,'results, prods y acts'!$D$2:$E$12,2,FALSE)),CONCATENATE(C78,". ")) -> P1. Asistencia técnica | E78: {=IFERROR(INDEX(_xlfn.TEXTSPLIT(I78,"."),2)&"."&INDEX(_xlfn.TEXTSPLIT(I78,"."),3),"")} -> P1.2 | F78: =IFERROR(CONCATENATE(E78,". ",VLOOKUP(E78,'results, prods y acts'!$G$2:$H$16,2,FALSE)),"") -> P1.2. Acompañamiento | G78: A nivel GSN | I78: R3.P1.2.7 | J78: Acompañamiento en el proceso de cumplimiento del Programa de Incentivos de Mejora de la Gestión Municipal. | K78: =CONCATENATE(I78,". ",J78) -> R3.P1.2.7. Acompañamiento en el proceso de cumplimiento del Programa de Incentivos de Mejora de la Gestión Municipal. | L78: Número de acompañamientos | M78: Acompañamiento | N78: Ficha de Seguimiento | O78: MPs Cumplimiento metas del Programa de Incentivos | R78: 6 | V78: 5 | AA78: 5 | AB78: =SUM(P78:AA78) -> 16
A79: R3 | B79: =IFERROR(CONCATENATE(A79,". ",VLOOKUP(A79,'results, prods y acts'!$A$2:$B$8,2,FALSE)),"") -> R3. Los procesos priorizados de recaudación del impuesto predial en los Gobiernos Locales son más eficaces y eficientes | C79: P2 | D79: =IFERROR(CONCATENATE(C79,". ",VLOOKUP(C79,'results, prods y acts'!$D$2:$E$12,2,FALSE)),CONCATENATE(C79,". ")) -> P2. Fortalecimiento de capacidades | E79: {=IFERROR(INDEX(_xlfn.TEXTSPLIT(I79,"."),2)&"."&INDEX(_xlfn.TEXTSPLIT(I79,"."),3),"")} -> P2.3 | F79: =IFERROR(CONCATENATE(E79,". ",VLOOKUP(E79,'results, prods y acts'!$G$2:$H$16,2,FALSE)),"") -> P2.3. Capacitación ad hoc | G79: A nivel GSN | I79: R3.P2.3.1 | J79: Capacitaciones ad hoc al personal de la administración tributaria de los municipios, sobre diversos aspectos de la tributación municipal. | K79: =CONCATENATE(I79,". ",J79) -> R3.P2.3.1. Capacitaciones ad hoc al personal de la administración tributaria de los municipios, sobre diversos aspectos de la tributación municipal. | L79: Número de Capacitaciones ad hoc | M79: Capacitación | N79: Informe y Actas | O79: Personal de la administración tributaria de los municipios con mayores conocimientos sobre normatividad de tributación municipal. | R79: 1 | S79: 1 | U79: 1 | V79: 1 | X79: 2 | AB79: =SUM(P79:AA79) -> 6
A80: R3 | B80: =IFERROR(CONCATENATE(A80,". ",VLOOKUP(A80,'results, prods y acts'!$A$2:$B$8,2,FALSE)),"") -> R3. Los procesos priorizados de recaudación del impuesto predial en los Gobiernos Locales son más eficaces y eficientes | C80: P2 | D80: =IFERROR(CONCATENATE(C80,". ",VLOOKUP(C80,'results, prods y acts'!$D$2:$E$12,2,FALSE)),CONCATENATE(C80,". ")) -> P2. Fortalecimiento de capacidades | E80: {=IFERROR(INDEX(_xlfn.TEXTSPLIT(I80,"."),2)&"."&INDEX(_xlfn.TEXTSPLIT(I80,"."),3),"")} -> P2.3 | F80: =IFERROR(CONCATENATE(E80,". ",VLOOKUP(E80,'results, prods y acts'!$G$2:$H$16,2,FALSE)),"") -> P2.3. Capacitación ad hoc | G80: A nivel GSN | I80: R3.P2.3.2 | J80: Cursos y/o Diplomado al personal de la administración tributaria de las municipalidades, sobre diversos aspectos de la tributación municipal. | K80: =CONCATENATE(I80,". ",J80) -> R3.P2.3.2. Cursos y/o Diplomado al personal de la administración tributaria de las municipalidades, sobre diversos aspectos de la tributación municipal. | L80: Número de Cursos o Diplomados | M80: Curso y/o Diplomado | N80: Informe y Actas | O80: Personal de la administración tributaria de los municipios con mayores conocimientos sobre normatividad de tributación municipal. | V80: 1 | AB80: =SUM(P80:AA80) -> 1
A81: R3 | B81: =IFERROR(CONCATENATE(A81,". ",VLOOKUP(A81,'results, prods y acts'!$A$2:$B$8,2,FALSE)),"") -> R3. Los procesos priorizados de recaudación del impuesto predial en los Gobiernos Locales son más eficaces y eficientes | C81: P2 | D81: =IFERROR(CONCATENATE(C81,". ",VLOOKUP(C81,'results, prods y acts'!$D$2:$E$12,2,FALSE)),CONCATENATE(C81,". ")) -> P2. Fortalecimiento de capacidades | E81: {=IFERROR(INDEX(_xlfn.TEXTSPLIT(I81,"."),2)&"."&INDEX(_xlfn.TEXTSPLIT(I81,"."),3),"")} -> P2.5 | F81: =IFERROR(CONCATENATE(E81,". ",VLOOKUP(E81,'results, prods y acts'!$G$2:$H$16,2,FALSE)),"") -> P2.5. Charla | G81: A nivel GSN | I81: R3.P2.5.1 | J81: Charla al personal de la administración tributaria de Municipalidades, sobre diversos aspectos de la tributación municipal. | K81: =CONCATENATE(I81,". ",J81) -> R3.P2.5.1. Charla al personal de la administración tributaria de Municipalidades, sobre diversos aspectos de la tributación municipal. | L81: Número de Charlas | M81: MPs | N81: Informe y Actas | O81: Municipalidades con mayores conocimientos sobre normatividad de tributación municipal. | Q81: 5 | T81: 6 | W81: 5 | Z81: 6 | AB81: =SUM(P81:AA81) -> 22
A82: R3 | B82: =IFERROR(CONCATENATE(A82,". ",VLOOKUP(A82,'results, prods y acts'!$A$2:$B$8,2,FALSE)),"") -> R3. Los procesos priorizados de recaudación del impuesto predial en los Gobiernos Locales son más eficaces y eficientes | C82: P3 | D82: =IFERROR(CONCATENATE(C82,". ",VLOOKUP(C82,'results, prods y acts'!$D$2:$E$12,2,FALSE)),CONCATENATE(C82,". ")) -> P3. Instrumentos de mejora de la gestión | E82: {=IFERROR(INDEX(_xlfn.TEXTSPLIT(I82,"."),2)&"."&INDEX(_xlfn.TEXTSPLIT(I82,"."),3),"")} -> P3.3 | F82: =IFERROR(CONCATENATE(E82,". ",VLOOKUP(E82,'results, prods y acts'!$G$2:$H$16,2,FALSE)),"") | G82: A nivel GSN | I82: R3.P3.3.1 | J82: Propuesta de reforma técnico-administrativa que promuevan actualizaciones y mejoras de la normatividad Tributaria Municipal | K82: =CONCATENATE(I82,". ",J82) -> R3.P3.3.1. Propuesta de reforma técnico-administrativa que promuevan actualizaciones y mejoras de la normatividad Tributaria Municipal | L82: Número de propuestas elaborada | M82: Propuesta | N82: Informe | O82: MPs promueven mejoras en la normatividad tributaria. | Y82: 2 | AB82: =SUM(P82:AA82) -> 2
A83: R3 | B83: =IFERROR(CONCATENATE(A83,". ",VLOOKUP(A83,'results, prods y acts'!$A$2:$B$8,2,FALSE)),"") -> R3. Los procesos priorizados de recaudación del impuesto predial en los Gobiernos Locales son más eficaces y eficientes | C83: P4 | D83: =IFERROR(CONCATENATE(C83,". ",VLOOKUP(C83,'results, prods y acts'!$D$2:$E$12,2,FALSE)),CONCATENATE(C83,". ")) -> P4. Tecnologia de la Informacion / Instrumentos de innovación | E83: {=IFERROR(INDEX(_xlfn.TEXTSPLIT(I83,"."),2)&"."&INDEX(_xlfn.TEXTSPLIT(I83,"."),3),"")} -> P4.2 | F83: =IFERROR(CONCATENATE(E83,". ",VLOOKUP(E83,'results, prods y acts'!$G$2:$H$16,2,FALSE)),"") -> P4.2. Intervención costo-efectivaaa | G83: A nivel GSN | I83: R3.P4.2.1 | J83: Propuestas costo-efectiva para la implementación de programas de fiscalización tributaria, que se sustenten en los ingresos obtenidos de la propia fiscalización | K83: =CONCATENATE(I83,". ",J83) -> R3.P4.2.1. Propuestas costo-efectiva para la implementación de programas de fiscalización tributaria, que se sustenten en los ingresos obtenidos de la propia fiscalización | L83: Número de Propuestas | M83: Propuesta | N83: Documento | O83: Propuestas de incremento en emisión tributaria por fiscalización. | V83: 1 | AB83: =SUM(P83:AA83) -> 1
A84: R3 | B84: =IFERROR(CONCATENATE(A84,". ",VLOOKUP(A84,'results, prods y acts'!$A$2:$B$8,2,FALSE)),"") -> R3. Los procesos priorizados de recaudación del impuesto predial en los Gobiernos Locales son más eficaces y eficientes | C84: P4 | D84: =IFERROR(CONCATENATE(C84,". ",VLOOKUP(C84,'results, prods y acts'!$D$2:$E$12,2,FALSE)),CONCATENATE(C84,". ")) -> P4. Tecnologia de la Informacion / Instrumentos de innovación | E84: {=IFERROR(INDEX(_xlfn.TEXTSPLIT(I84,"."),2)&"."&INDEX(_xlfn.TEXTSPLIT(I84,"."),3),"")} -> P4.2 | F84: =IFERROR(CONCATENATE(E84,". ",VLOOKUP(E84,'results, prods y acts'!$G$2:$H$16,2,FALSE)),"") -> P4.2. Intervención costo-efectivaaa | G84: A nivel GSN | I84: R3.P4.2.2 | J84: Propuestas costo-efectiva para la implementación de estrategias dirigidas al incremento de la recaudación predial | K84: =CONCATENATE(I84,". ",J84) -> R3.P4.2.2. Propuestas costo-efectiva para la implementación de estrategias dirigidas al incremento de la recaudación predial | L84: Número de Propuestas | M84: Propuesta | N84: Documento | O84: Propuestas de acciones para promover incremento de recaudación predial | X84: 2 | AB84: =SUM(P84:AA84) -> 2
A85: R3 | B85: =IFERROR(CONCATENATE(A85,". ",VLOOKUP(A85,'results, prods y acts'!$A$2:$B$8,2,FALSE)),"") -> R3. Los procesos priorizados de recaudación del impuesto predial en los Gobiernos Locales son más eficaces y eficientes | C85: P5 | D85: =IFERROR(CONCATENATE(C85,". ",VLOOKUP(C85,'results, prods y acts'!$D$2:$E$12,2,FALSE)),CONCATENATE(C85,". ")) -> P5. Instrumentos de Gestión del Conocimiento (Publicaciones) | E85: {=IFERROR(INDEX(_xlfn.TEXTSPLIT(I85,"."),2)&"."&INDEX(_xlfn.TEXTSPLIT(I85,"."),3),"")} -> P5.2 | F85: =IFERROR(CONCATENATE(E85,". ",VLOOKUP(E85,'results, prods y acts'!$G$2:$H$16,2,FALSE)),"") -> P5.2. Documentos de buenas prácticas y lecciones aprendidas | G85: A nivel GSN | I85: R3.P5.2.1 | J85: Documentos de buenas prácticas | K85: =CONCATENATE(I85,". ",J85) -> R3.P5.2.1. Documentos de buenas prácticas | L85: Número de documentos | M85: Documento | N85: Documento | O85: Difusión de buenas prácticas implementadas en los GSN | AA85: 1 | AB85: =SUM(P85:AA85) -> 1
A86: R3 | B86: =IFERROR(CONCATENATE(A86,". ",VLOOKUP(A86,'results, prods y acts'!$A$2:$B$8,2,FALSE)),"") -> R3. Los procesos priorizados de recaudación del impuesto predial en los Gobiernos Locales son más eficaces y eficientes | C86: P5 | D86: =IFERROR(CONCATENATE(C86,". ",VLOOKUP(C86,'results, prods y acts'!$D$2:$E$12,2,FALSE)),CONCATENATE(C86,". ")) -> P5. Instrumentos de Gestión del Conocimiento (Publicaciones) | E86: {=IFERROR(INDEX(_xlfn.TEXTSPLIT(I86,"."),2)&"."&INDEX(_xlfn.TEXTSPLIT(I86,"."),3),"")} -> P5.3 | F86: =IFERROR(CONCATENATE(E86,". ",VLOOKUP(E86,'results, prods y acts'!$G$2:$H$16,2,FALSE)),"") -> P5.3. Documentos de política | G86: A nivel GSN | I86: R3.P5.3.1 | J86: Documento de politica | K86: =CONCATENATE(I86,". ",J86) -> R3.P5.3.1. Documento de politica | L86: Número de documentos | M86: Documento | N86: Documento/Presentación | O86: GSN tienen una gestión más ordenada y transparente | U86: 1 | Z86: 1 | AB86: =SUM(P86:AA86) -> 2
A87: R3 | B87: =IFERROR(CONCATENATE(A87,". ",VLOOKUP(A87,'results, prods y acts'!$A$2:$B$8,2,FALSE)),"") -> R3. Los procesos priorizados de recaudación del impuesto predial en los Gobiernos Locales son más eficaces y eficientes | C87: P6 | D87: =IFERROR(CONCATENATE(C87,". ",VLOOKUP(C87,'results, prods y acts'!$D$2:$E$12,2,FALSE)),CONCATENATE(C87,". ")) -> P6. | F87: =IFERROR(CONCATENATE(E87,". ",VLOOKUP(E87,'results, prods y acts'!$G$2:$H$16,2,FALSE)),"") | G87: A nivel Nacional | H87: MEF - Dirección General de Política Macroeconómica y Descentralización Fiscal | I87: R3.P6.1.1 | J87: Reunión de coordinación con la Dirección de Política y Descentralización Fiscal respecto a la asistencia técnica de la implementación y capacitación de uso del nuevo Sistema de Recaudación Tributaria Municipal (SRTM), la vinculación con el catastro y de programas y/o actividades dirigidas a mejorar la recaudación tributaria de los GL. | K87: =CONCATENATE(I87,". ",J87) -> R3.P6.1.1. Reunión de coordinación con la Dirección de Política y Descentralización Fiscal respecto a la asistencia técnica de la implementación y capacitación de uso del nuevo Sistema de Recaudación Tributaria Municipal (SRTM), la vinculación con el catastro y de programas y/o actividades dirigidas a mejorar la recaudación tributaria de los GL. | L87: Número de reuniones | M87: Reunión | N87: Informe | O87: Fortalecer conocimiento para asistencia técnica y retroalimentación. | Q87: 1 | T87: 1 | W87: 1 | Z87: 1 | AB87: =SUM(P87:AA87) -> 4
A88: R3 | B88: =IFERROR(CONCATENATE(A88,". ",VLOOKUP(A88,'results, prods y acts'!$A$2:$B$8,2,FALSE)),"") -> R3. Los procesos priorizados de recaudación del impuesto predial en los Gobiernos Locales son más eficaces y eficientes | D88: =IFERROR(CONCATENATE(C88,". ",VLOOKUP(C88,'results, prods y acts'!$D$2:$E$12,2,FALSE)),CONCATENATE(C88,". ")) -> . | F88: =IFERROR(CONCATENATE(E88,". ",VLOOKUP(E88,'results, prods y acts'!$G$2:$H$16,2,FALSE)),"") | G88: A nivel Nacional | H88: MEF - Dirección General de Políticas de Ingresos Públicos | I88: R3.P6.1.2 | J88: Reunión de coordinación con la Dirección General de Políticas de Ingresos Públicos del Ministerio de Economía y Finanzas vinculado al desarrollo del Programa de Apoyo Presupuestario (PAP) impulsado por SECO, para promover actividades que permitan potenciar los resultados esperados de la intervención | K88: =CONCATENATE(I88,". ",J88) -> R3.P6.1.2. Reunión de coordinación con la Dirección General de Políticas de Ingresos Públicos del Ministerio de Economía y Finanzas vinculado al desarrollo del Programa de Apoyo Presupuestario (PAP) impulsado por SECO, para promover actividades que permitan potenciar los resultados esperados de la intervención | L88: Número de reuniones | M88: Reunión | N88: Informe | O88: Fortalecer conocimiento para asistencia técnica y retroalimentación. | R88: 1 | AB88: =SUM(P88:AA88) -> 1
A89: R4 | B89: =IFERROR(CONCATENATE(A89,". ",VLOOKUP(A89,'results, prods y acts'!$A$2:$B$8,2,FALSE)),"") -> R4. El control interno y la integridad pública del GSN se fortalecen | C89: P1 | D89: =IFERROR(CONCATENATE(C89,". ",VLOOKUP(C89,'results, prods y acts'!$D$2:$E$12,2,FALSE)),CONCATENATE(C89,". ")) -> P1. Asistencia técnica | E89: {=IFERROR(INDEX(_xlfn.TEXTSPLIT(I89,"."),2)&"."&INDEX(_xlfn.TEXTSPLIT(I89,"."),3),"")} -> P1.1 | F89: =IFERROR(CONCATENATE(E89,". ",VLOOKUP(E89,'results, prods y acts'!$G$2:$H$16,2,FALSE)),"") -> P1.1. Taller | G89: A nivel GSN | I89: R4.P1.1.1 | J89: Talleres de gestión de riesgos o reflexión ética dirigidos a los equipos técnicos de los GN y GSN que brindan SPP | K89: =CONCATENATE(I89,". ",J89) -> R4.P1.1.1. Talleres de gestión de riesgos o reflexión ética dirigidos a los equipos técnicos de los GN y GSN que brindan SPP | L89: Número de talleres | M89: Taller | N89: Informe | O89: GSN elabora o actualiza plan de control interno para SPP | R89: 1 | S89: 2 | U89: 1 | V89: 2 | X89: 1 | Y89: 2 | Z89: 1 | AB89: =SUM(P89:AA89) -> 10
A90: R4 | B90: =IFERROR(CONCATENATE(A90,". ",VLOOKUP(A90,'results, prods y acts'!$A$2:$B$8,2,FALSE)),"") -> R4. El control interno y la integridad pública del GSN se fortalecen | C90: P1 | D90: =IFERROR(CONCATENATE(C90,". ",VLOOKUP(C90,'results, prods y acts'!$D$2:$E$12,2,FALSE)),CONCATENATE(C90,". ")) -> P1. Asistencia técnica | E90: {=IFERROR(INDEX(_xlfn.TEXTSPLIT(I90,"."),2)&"."&INDEX(_xlfn.TEXTSPLIT(I90,"."),3),"")} -> P1.2 | F90: =IFERROR(CONCATENATE(E90,". ",VLOOKUP(E90,'results, prods y acts'!$G$2:$H$16,2,FALSE)),"") -> P1.2. Acompañamiento | G90: A nivel GSN | I90: R4.P1.2.1 | J90: Acompañamiento al equipo coordinador de los GR y MP en la elaboración y seguimiento de los planes de control interno de SPP, e implementación del modelo de integridad en el marco del Programa GFP Subnacional | K90: =CONCATENATE(I90,". ",J90) -> R4.P1.2.1. Acompañamiento al equipo coordinador de los GR y MP en la elaboración y seguimiento de los planes de control interno de SPP, e implementación del modelo de integridad en el marco del Programa GFP Subnacional | L90: Número de acompañamientos | M90: Acompañamiento | N90: Ficha de seguimiento | O90: GSN elabora, actualiza y efectúa seguimiento a plan de control interno para SPP | R90: 2 | S90: 1 | T90: 1 | V90: 1 | W90: 1 | X90: 1 | Y90: 1 | Z90: 2 | AB90: =SUM(P90:AA90) -> 10
A91: R4 | B91: =IFERROR(CONCATENATE(A91,". ",VLOOKUP(A91,'results, prods y acts'!$A$2:$B$8,2,FALSE)),"") -> R4. El control interno y la integridad pública del GSN se fortalecen | C91: P1 | D91: =IFERROR(CONCATENATE(C91,". ",VLOOKUP(C91,'results, prods y acts'!$D$2:$E$12,2,FALSE)),CONCATENATE(C91,". ")) -> P1. Asistencia técnica | E91: {=IFERROR(INDEX(_xlfn.TEXTSPLIT(I91,"."),2)&"."&INDEX(_xlfn.TEXTSPLIT(I91,"."),3),"")} -> P1.2 | F91: =IFERROR(CONCATENATE(E91,". ",VLOOKUP(E91,'results, prods y acts'!$G$2:$H$16,2,FALSE)),"") -> P1.2. Acompañamiento | G91: A nivel GSN | I91: R4.P1.2.2 | J91: Acompañamiento al órgano rector en integridad y entidades del GN priorizadas en la implementación del modelo de integridad | K91: =CONCATENATE(I91,". ",J91) -> R4.P1.2.2. Acompañamiento al órgano rector en integridad y entidades del GN priorizadas en la implementación del modelo de integridad | L91: Número de Acompañamientos | M91: Acompañamiento | N91: Ficha de Seguimiento | O91: El órgano rector en integridad y entidades priorizadas del GN fortalecen el modelo de integridad | S91: 1 | U91: 1 | X91: 1 | Y91: 1 | AB91: =SUM(P91:AA91) -> 4
A92: R4 | B92: =IFERROR(CONCATENATE(A92,". ",VLOOKUP(A92,'results, prods y acts'!$A$2:$B$8,2,FALSE)),"") -> R4. El control interno y la integridad pública del GSN se fortalecen | C92: P2 | D92: =IFERROR(CONCATENATE(C92,". ",VLOOKUP(C92,'results, prods y acts'!$D$2:$E$12,2,FALSE)),CONCATENATE(C92,". ")) -> P2. Fortalecimiento de capacidades | E92: {=IFERROR(INDEX(_xlfn.TEXTSPLIT(I92,"."),2)&"."&INDEX(_xlfn.TEXTSPLIT(I92,"."),3),"")} -> P2.1 | F92: =IFERROR(CONCATENATE(E92,". ",VLOOKUP(E92,'results, prods y acts'!$G$2:$H$16,2,FALSE)),"") -> P2.1. Cursos | G92: A nivel GSN | I92: R4.P2.1.1 | J92: Curso virtual a los GSN en control interno y/o gestión de riesgos, para optimizar la provisión de SPP | K92: =CONCATENATE(I92,". ",J92) -> R4.P2.1.1. Curso virtual a los GSN en control interno y/o gestión de riesgos, para optimizar la provisión de SPP | L92: Número de cursos virtuales | M92: Curso | N92: Informe | O92: UE de GSN que entregan SPP conocen y aplican la gestión de riesgos | R92: 1 | V92: 1 | Y92: 1 | AB92: =SUM(P92:AA92) -> 3
A93: R4 | B93: =IFERROR(CONCATENATE(A93,". ",VLOOKUP(A93,'results, prods y acts'!$A$2:$B$8,2,FALSE)),"") -> R4. El control interno y la integridad pública del GSN se fortalecen | C93: P2 | D93: =IFERROR(CONCATENATE(C93,". ",VLOOKUP(C93,'results, prods y acts'!$D$2:$E$12,2,FALSE)),CONCATENATE(C93,". ")) -> P2. Fortalecimiento de capacidades | E93: {=IFERROR(INDEX(_xlfn.TEXTSPLIT(I93,"."),2)&"."&INDEX(_xlfn.TEXTSPLIT(I93,"."),3),"")} -> P2.3 | F93: =IFERROR(CONCATENATE(E93,". ",VLOOKUP(E93,'results, prods y acts'!$G$2:$H$16,2,FALSE)),"") -> P2.3. Capacitación ad hoc | G93: A nivel GSN | I93: R4.P2.3.1 | J93: Capacitación ad-hoc a los GSN sobre gestión de riesgos, orientada a la provisión de SPP | K93: =CONCATENATE(I93,". ",J93) -> R4.P2.3.1. Capacitación ad-hoc a los GSN sobre gestión de riesgos, orientada a la provisión de SPP | L93: Número de capacitaciones ad hoc | M93: Capacitación | N93: Informe | O93: UE de GSN que entregan SPP conocen la gestión de riesgos | S93: 1 | U93: 1 | W93: 1 | X93: 1 | Y93: 1 | Z93: 1 | AB93: =SUM(P93:AA93) -> 6
A94: R4 | B94: =IFERROR(CONCATENATE(A94,". ",VLOOKUP(A94,'results, prods y acts'!$A$2:$B$8,2,FALSE)),"") -> R4. El control interno y la integridad pública del GSN se fortalecen | C94: P2 | D94: =IFERROR(CONCATENATE(C94,". ",VLOOKUP(C94,'results, prods y acts'!$D$2:$E$12,2,FALSE)),CONCATENATE(C94,". ")) -> P2. Fortalecimiento de capacidades | E94: {=IFERROR(INDEX(_xlfn.TEXTSPLIT(I94,"."),2)&"."&INDEX(_xlfn.TEXTSPLIT(I94,"."),3),"")} -> P2.5 | F94: =IFERROR(CONCATENATE(E94,". ",VLOOKUP(E94,'results, prods y acts'!$G$2:$H$16,2,FALSE)),"") -> P2.5. Charla | G94: A nivel GSN | I94: R4.P2.5.1 | J94: Charlas informativas y charlas de sensibilización en materia de control interno o integridad pública, dirigidas a funcionarios y servidores de los GSN que participan en la provisión de los SPP | K94: =CONCATENATE(I94,". ",J94) -> R4.P2.5.1. Charlas informativas y charlas de sensibilización en materia de control interno o integridad pública, dirigidas a funcionarios y servidores de los GSN que participan en la provisión de los SPP | L94: Número de charlas | M94: Charla | N94: Informe | O94: GSN conocen la importancia del control interno. | S94: 1 | U94: 1 | W94: 1 | Y94: 2 | Z94: 1 | AB94: =SUM(P94:AA94) -> 6
A95: R4 | B95: =IFERROR(CONCATENATE(A95,". ",VLOOKUP(A95,'results, prods y acts'!$A$2:$B$8,2,FALSE)),"") -> R4. El control interno y la integridad pública del GSN se fortalecen | C95: P2 | D95: =IFERROR(CONCATENATE(C95,". ",VLOOKUP(C95,'results, prods y acts'!$D$2:$E$12,2,FALSE)),CONCATENATE(C95,". ")) -> P2. Fortalecimiento de capacidades | E95: {=IFERROR(INDEX(_xlfn.TEXTSPLIT(I95,"."),2)&"."&INDEX(_xlfn.TEXTSPLIT(I95,"."),3),"")} -> P2.5 | F95: =IFERROR(CONCATENATE(E95,". ",VLOOKUP(E95,'results, prods y acts'!$G$2:$H$16,2,FALSE)),"") -> P2.5. Charla | G95: A nivel GSN | I95: R4.P2.5.2 | J95: Charlas de sensibilización para la reflexión ética en la toma de decisiones y la internalización de valores, dirigidos a servidores en Unidades Orgánicas a cargo de coordinar, ejecutar y controlar los procesos de contratación pública en los GR y MP que brindan SPP | K95: =CONCATENATE(I95,". ",J95) -> R4.P2.5.2. Charlas de sensibilización para la reflexión ética en la toma de decisiones y la internalización de valores, dirigidos a servidores en Unidades Orgánicas a cargo de coordinar, ejecutar y controlar los procesos de contratación pública en los GR y MP que brindan SPP | L95: Número de charlas | M95: Charla | N95: Informe | O95: GSN que brindan SPP reconocen la importancia de los valores en la toma de decisiones | S95: 1 | U95: 1 | V95: 1 | W95: 1 | Y95: 1 | Z95: 1 | AB95: =SUM(P95:AA95) -> 6
A96: R4 | B96: =IFERROR(CONCATENATE(A96,". ",VLOOKUP(A96,'results, prods y acts'!$A$2:$B$8,2,FALSE)),"") -> R4. El control interno y la integridad pública del GSN se fortalecen | C96: P2 | D96: =IFERROR(CONCATENATE(C96,". ",VLOOKUP(C96,'results, prods y acts'!$D$2:$E$12,2,FALSE)),CONCATENATE(C96,". ")) -> P2. Fortalecimiento de capacidades | E96: {=IFERROR(INDEX(_xlfn.TEXTSPLIT(I96,"."),2)&"."&INDEX(_xlfn.TEXTSPLIT(I96,"."),3),"")} -> P2.5 | F96: =IFERROR(CONCATENATE(E96,". ",VLOOKUP(E96,'results, prods y acts'!$G$2:$H$16,2,FALSE)),"") -> P2.5. Charla | G96: A nivel GSN | I96: R4.P2.5.3 | J96: Charlas en materia de control interno, modelo de integridad, gestión de riesgos, ética y temas relacionados dirigidas a funcionarios y servidores de los GN | K96: =CONCATENATE(I96,". ",J96) -> R4.P2.5.3. Charlas en materia de control interno, modelo de integridad, gestión de riesgos, ética y temas relacionados dirigidas a funcionarios y servidores de los GN | L96: Número de charlas | M96: Charla | N96: Informe | O96: Los GN reconocen la importancia de los valores e integridad en la toma de decisiones | U96: 1 | X96: 1 | AB96: =SUM(P96:AA96) -> 2
A97: R4 | B97: =IFERROR(CONCATENATE(A97,". ",VLOOKUP(A97,'results, prods y acts'!$A$2:$B$8,2,FALSE)),"") -> R4. El control interno y la integridad pública del GSN se fortalecen | C97: P3 | D97: =IFERROR(CONCATENATE(C97,". ",VLOOKUP(C97,'results, prods y acts'!$D$2:$E$12,2,FALSE)),CONCATENATE(C97,". ")) -> P3. Instrumentos de mejora de la gestión | E97: {=IFERROR(INDEX(_xlfn.TEXTSPLIT(I97,"."),2)&"."&INDEX(_xlfn.TEXTSPLIT(I97,"."),3),"")} -> P3.4 | F97: =IFERROR(CONCATENATE(E97,". ",VLOOKUP(E97,'results, prods y acts'!$G$2:$H$16,2,FALSE)),"") -> P3.4. Propuesta de modificación técnico-administrativa a nivel institucional | G97: A nivel GSN | I97: R4.P3.4.1 | J97: Propuesta de directiva/protocolo/lineamientos sobre control interno o modelo de integridad a nivel de GSN | K97: =CONCATENATE(I97,". ",J97) -> R4.P3.4.1. Propuesta de directiva/protocolo/lineamientos sobre control interno o modelo de integridad a nivel de GSN | L97: Número de propuestas | M97: Propuesta | N97: Informe | O97: GSNs tienen una gestión mas ordenada y transparente | W97: 1 | AB97: =SUM(P97:AA97) -> 1
A98: R4 | B98: =IFERROR(CONCATENATE(A98,". ",VLOOKUP(A98,'results, prods y acts'!$A$2:$B$8,2,FALSE)),"") -> R4. El control interno y la integridad pública del GSN se fortalecen | C98: P3 | D98: =IFERROR(CONCATENATE(C98,". ",VLOOKUP(C98,'results, prods y acts'!$D$2:$E$12,2,FALSE)),CONCATENATE(C98,". ")) -> P3. Instrumentos de mejora de la gestión | E98: {=IFERROR(INDEX(_xlfn.TEXTSPLIT(I98,"."),2)&"."&INDEX(_xlfn.TEXTSPLIT(I98,"."),3),"")} -> P3.5 | F98: =IFERROR(CONCATENATE(E98,". ",VLOOKUP(E98,'results, prods y acts'!$G$2:$H$16,2,FALSE)),"") -> P3.5. Propuesta de modificación técnico-administrativa a nivel sectorial | G98: A nivel GSN | I98: R4.P3.5.1 | J98: Propuesta de reforma tecnico administrativa sobre control interno o modelo de integridad a nivel de sector (CGR o SIP) | K98: =CONCATENATE(I98,". ",J98) -> R4.P3.5.1. Propuesta de reforma tecnico administrativa sobre control interno o modelo de integridad a nivel de sector (CGR o SIP) | L98: Número de propuestas | M98: Propuesta | N98: Informe | O98: GSNs tienen una gestión mas ordenada y transparente | Z98: 1 | AB98: =SUM(P98:AA98) -> 1
A99: R4 | B99: =IFERROR(CONCATENATE(A99,". ",VLOOKUP(A99,'results, prods y acts'!$A$2:$B$8,2,FALSE)),"") -> R4. El control interno y la integridad pública del GSN se fortalecen | C99: P4 | D99: =IFERROR(CONCATENATE(C99,". ",VLOOKUP(C99,'results, prods y acts'!$D$2:$E$12,2,FALSE)),CONCATENATE(C99,". ")) -> P4. Tecnologia de la Informacion / Instrumentos de innovación | E99: {=IFERROR(INDEX(_xlfn.TEXTSPLIT(I99,"."),2)&"."&INDEX(_xlfn.TEXTSPLIT(I99,"."),3),"")} -> P4.1 | F99: =IFERROR(CONCATENATE(E99,". ",VLOOKUP(E99,'results, prods y acts'!$G$2:$H$16,2,FALSE)),"") -> P4.1. Estrategia para la eficiencia de procesos | G99: A nivel GSN | I99: R4.P4.1.1 | J99: Propuesta de eficiencia de procesos en control interno o modelo de integridad | K99: =CONCATENATE(I99,". ",J99) -> R4.P4.1.1. Propuesta de eficiencia de procesos en control interno o modelo de integridad | L99: Número de propuestas | M99: Propuesta | N99: Informe | AA99: 1 | AB99: =SUM(P99:AA99) -> 1
A100: R4 | B100: =IFERROR(CONCATENATE(A100,". ",VLOOKUP(A100,'results, prods y acts'!$A$2:$B$8,2,FALSE)),"") -> R4. El control interno y la integridad pública del GSN se fortalecen | C100: P5 | D100: =IFERROR(CONCATENATE(C100,". ",VLOOKUP(C100,'results, prods y acts'!$D$2:$E$12,2,FALSE)),CONCATENATE(C100,". ")) -> P5. Instrumentos de Gestión del Conocimiento (Publicaciones) | E100: {=IFERROR(INDEX(_xlfn.TEXTSPLIT(I100,"."),2)&"."&INDEX(_xlfn.TEXTSPLIT(I100,"."),3),"")} -> P5.1 | F100: =IFERROR(CONCATENATE(E100,". ",VLOOKUP(E100,'results, prods y acts'!$G$2:$H$16,2,FALSE)),"") -> P5.1. Documentos de trabajo | G100: A nivel GSN | I100: R4.P5.1.1 | J100: Documentos de trabajo en control interno / modelo de integridad pública | K100: =CONCATENATE(I100,". ",J100) -> R4.P5.1.1. Documentos de trabajo en control interno / modelo de integridad pública | L100: Número de publicaciones | M100: Documento | N100: Documento | O100: Difusión de artículos académicos especializados sobre control interno o modelo de integridad | V100: 1 | AB100: =SUM(P100:AA100) -> 1
...

Sheet POA2026_ej (2)
A1: Resultado_cod | B1: Resultado | C1: Producto_cod | D1: Producto | E1: Tipo_producto_cod | F1: Tipo de producto | G1: Nivel | H1: Entidad_p6 | I1: Actividad_cod | J1: Actividad_name | K1: Actividad | L1: Indicador | M1: Unidad de medida | N1: Medio de verificación | O1: Logro Esperado | P1: ene_pl | Q1: feb_pl | R1: mar_pl | S1: abr_pl | T1: may_pl | U1: jun_pl | V1: jul_pl | W1: ago_pl | X1: set_pl | Y1: oct_pl | Z1: nov_pl | AA1: dic_pl | AB1: Pl_total | AC1: ene_ej | AD1: feb_ej | AE1: mar_ej | AF1: abr_ej | AG1: may_ej | AH1: jun_ej | AI1: jul_ej | AJ1: ago_ej | AK1: set_ej | AL1: oct_ej | AM1: nov_ej | AN1: dic_ej | AO1: Ej_total
A2: D1 | B2: =IFERROR(CONCATENATE(A2,". ",VLOOKUP(A2,'results, prods y acts'!$A$2:$B$8,2,FALSE)),"") -> D1. Los procesos estratégicos y de soporte se realizan de forma eficaz y eficiente | C2: D1.1 | D2: =IFERROR(CONCATENATE(C2,". ",VLOOKUP(C2,'results, prods y acts'!$D$2:$E$12,2,FALSE)),CONCATENATE(C2,". ")) -> D1.1. Informes semestrales | I2: D1.1.1 | J2: Envío a SECO | K2: =CONCATENATE(I2,". ",J2) -> D1.1.1. Envío a SECO | L2: Número de informes | M2: Informe | N2: Correo de envío | O2: Informes enviados en el tiempo esperado | Q2: 1 | W2: 1 | AB2: =SUM(P2:AA2) -> 2
A3: D1 | B3: =IFERROR(CONCATENATE(A3,". ",VLOOKUP(A3,'results, prods y acts'!$A$2:$B$8,2,FALSE)),"") -> D1. Los procesos estratégicos y de soporte se realizan de forma eficaz y eficiente | C3: D1.1 | D3: =IFERROR(CONCATENATE(C3,". ",VLOOKUP(C3,'results, prods y acts'!$D$2:$E$12,2,FALSE)),CONCATENATE(C3,". ")) -> D1.1. Informes semestrales | I3: D1.1.2 | J3: Absolución de comentarios | K3: =CONCATENATE(I3,". ",J3) -> D1.1.2. Absolución de comentarios | L3: Número de respuestas | M3: Informe | N3: Correo de envío | O3: Informes enviados en el tiempo esperado | Q3: 1 | W3: 1 | AB3: =SUM(P3:AA3) -> 2
A4: R1 | B4: =IFERROR(CONCATENATE(A4,". ",VLOOKUP(A4,'results, prods y acts'!$A$2:$B$8,2,FALSE)),"") -> R1. Los procesos de gestión de gasto corriente vinculados a los servicios básicos priorizados a cargo de los GSN son más eficaces y eficientes | C4: P2 | D4: =IFERROR(CONCATENATE(C4,". ",VLOOKUP(C4,'results, prods y acts'!$D$2:$E$12,2,FALSE)),CONCATENATE(C4,". ")) -> P2. Fortalecimiento de capacidades | E4: {=IFERROR(INDEX(_xlfn.TEXTSPLIT(I4,"."),2)&"."&INDEX(_xlfn.TEXTSPLIT(I4,"."),3),"")} -> P2.1 | F4: =IFERROR(CONCATENATE(E4,". ",VLOOKUP(E4,'results, prods y acts'!$G$2:$H$16,2,FALSE)),"") -> P2.1. Cursos | G4: A nivel GSN | I4: R1.P2.1.2 | J4: Curso en Instrumentos de Sostenibilidad Financiera | K4: =CONCATENATE(I4,". ",J4) -> R1.P2.1.2. Curso en Instrumentos de Sostenibilidad Financiera | L4: Número de cursos | M4: Curso | N4: Informe | O4: Gerencias de recursos naturales capacitados en el uso de instrumentos de sostenibilidad financiera | Q4: 1 | AB4: =SUM(P4:AA4) -> 1
A5: CB | B5: =IFERROR(CONCATENATE(A5,". ",VLOOKUP(A5,'results, prods y acts'!$A$2:$B$8,2,FALSE)),"") -> CB. Conservación de la Biodiversidad y Lucha contra el Cambio Climático | C5: P3 | D5: =IFERROR(CONCATENATE(C5,". ",VLOOKUP(C5,'results, prods y acts'!$D$2:$E$12,2,FALSE)),CONCATENATE(C5,". ")) -> P3. Instrumentos de mejora de la gestión | E5: {=IFERROR(INDEX(_xlfn.TEXTSPLIT(I5,"."),2)&"."&INDEX(_xlfn.TEXTSPLIT(I5,"."),3),"")} -> P3.5 | F5: =IFERROR(CONCATENATE(E5,". ",VLOOKUP(E5,'results, prods y acts'!$G$2:$H$16,2,FALSE)),"") -> P3.5. Propuesta de modificación técnico-administrativa a nivel sectorial | G5: A nivel GSN | I5: CB.P3.5.1 | J5: Guía para la entrega de los servicios de vigilancia y control, en las fases de monitoreo y retroalimentación | K5: =CONCATENATE(I5,". ",J5) -> CB.P3.5.1. Guía para la entrega de los servicios de vigilancia y control, en las fases de monitoreo y retroalimentación | L5: Numero de propuestas | M5: Documento | N5: Guia o Protocolo | O5: SERNANP fortalece su institucionalidad en vigilancia y control | R5: 1 | AB5: =SUM(P5:AA5) -> 1
A6: CB | B6: =IFERROR(CONCATENATE(A6,". ",VLOOKUP(A6,'results, prods y acts'!$A$2:$B$8,2,FALSE)),"") -> CB. Conservación de la Biodiversidad y Lucha contra el Cambio Climático | C6: P5 | D6: =IFERROR(CONCATENATE(C6,". ",VLOOKUP(C6,'results, prods y acts'!$D$2:$E$12,2,FALSE)),CONCATENATE(C6,". ")) -> P5. Instrumentos de Gestión del Conocimiento (Publicaciones) | E6: {=IFERROR(INDEX(_xlfn.TEXTSPLIT(I6,"."),2)&"."&INDEX(_xlfn.TEXTSPLIT(I6,"."),3),"")} -> P5.2 | F6: =IFERROR(CONCATENATE(E6,". ",VLOOKUP(E6,'results, prods y acts'!$G$2:$H$16,2,FALSE)),"") -> P5.2. Documentos de buenas prácticas y lecciones aprendidas | G6: A nivel GSN | I6: CB.P5.2.1 | J6: Documento de Buenas practicas en el uso del Mapa de Actores | K6: =CONCATENATE(I6,". ",J6) -> CB.P5.2.1. Documento de Buenas practicas en el uso del Mapa de Actores | L6: Numero de publicaciones | M6: Documento | N6: Publicación | O6: Difusión de buenas practicas en el uso de Mapa de Actores | Y6: 1 | AB6: =SUM(P6:AA6) -> 1
A7: CB | B7: =IFERROR(CONCATENATE(A7,". ",VLOOKUP(A7,'results, prods y acts'!$A$2:$B$8,2,FALSE)),"") -> CB. Conservación de la Biodiversidad y Lucha contra el Cambio Climático | C7: P6 | D7: =IFERROR(CONCATENATE(C7,". ",VLOOKUP(C7,'results, prods y acts'!$D$2:$E$12,2,FALSE)),CONCATENATE(C7,". ")) -> P6. | F7: =IFERROR(CONCATENATE(E7,". ",VLOOKUP(E7,'results, prods y acts'!$G$2:$H$16,2,FALSE)),"") | G7: A nivel nacional | H7: Entes rectores | I7: CB.6.1 | J7: Planes de trabajo con entes rectores (SERNANP, OSINFOR, MINAM) | K7: =CONCATENATE(I7,". ",J7) -> CB.6.1. Planes de trabajo con entes rectores (SERNANP, OSINFOR, MINAM) | L7: Numeros de planes | M7: Planes | N7: Planes | O7: Establecer intervenciones articuladas con los órganos rectores en materia ambiental | Q7: 2 | U7: 1 | AB7: =SUM(P7:AA7) -> 3

Sheet results, prods y acts
A1: Codigo | B1: Resultado | D1: Codigo | E1: Producto | G1: Codigo | H1: Tipo de producto
A2: D1 | B2: Los procesos estratégicos y de soporte se realizan de forma eficaz y eficiente | D2: D1.1 | E2: Informes semestrales | G2: P1.1 | H2: Taller
A3: R1 | B3: Los procesos de gestión de gasto corriente vinculados a los servicios básicos priorizados a cargo de los GSN son más eficaces y eficientes | D3: D1.2 | E3: Planificación Operativa | G3: P1.2 | H3: Acompañamiento
A4: R2 | B4: Los procesos de gestión de gasto de capital vinculados a los servicios priorizados a cargo de los GSN son más eficaces y eficientes | D4: D1.3 | E4: Monitoreo y Evaluación | G4: P1.3 | H4: Reuniones de retroalimentación
A5: R3 | B5: Los procesos priorizados de recaudación del impuesto predial en los Gobiernos Locales son más eficaces y eficientes | D5: D1.4 | E5: Coordinación con socios, cooperantes y Programas de SECO | G5: P2.1 | H5: Cursos
A6: R4 | B6: El control interno y la integridad pública del GSN se fortalecen | D6: D1.5 | E6: Evaluación de los GSN | G6: P2.2 | H6: Diplomado
A7: R5 | B7: La capacidad de los operadores de justicia para recuperar activos ilícitos se consolida | D7: D1.6 | E7: Gestión del Conocimiento y Sostenibilidad | G7: P2.3 | H7: Capacitación ad hoc
A8: CB | B8: Conservación de la Biodiversidad y Lucha contra el Cambio Climático | D8: P1 | E8: Asistencia técnica | G8: P2.4 | H8: Programa de entrenamiento
D9: P2 | E9: Fortalecimiento de capacidades | G9: P2.5 | H9: Charla
D10: P3 | E10: Instrumentos de mejora de la gestión | G10: P3.4 | H10: Propuesta de modificación técnico-administrativa a nivel institucional
D11: P4 | E11: Tecnologia de la Informacion / Instrumentos de innovación | G11: P3.5 | H11: Propuesta de modificación técnico-administrativa a nivel sectorial
D12: P5 | E12: Instrumentos de Gestión del Conocimiento (Publicaciones) | G12: P4.1 | H12: Estrategia para la eficiencia de procesos
D13: P6 | G13: P4.2 | H13: Intervención costo-efectivaaa
G14: P5.1 | H14: Documentos de trabajo
G15: P5.2 | H15: Documentos de buenas prácticas y lecciones aprendidas
G16: P5.3 | H16: Documentos de política

Sheet Consultores
A1: Consultor | B1: Tipo | C1: Usuario | D1: Password | E1: Tipo consultor | F1: Área de Especialidad | G1: Entidad | H1: Resultado | I1: Componente | J1: Teléfono | K1: Correo electrónico | L1: Correo personal
A2: Admin | B2: admin | C2: admin | D2: admin1234 | E2: Dirección | F2: Dirección | G2: Todo el ámbito del Programa | H2: D,R,C
A3: Jorge Manrique | B3: user | C3: jorge.manrique | D3: jorge.manrique8724 | E3: Itinerante | F3: Conservación de Biodiversidad | G3: Todo el ámbito del Programa | H3: CB | I3: Gestión de las Finanzas Públicas | K3: jorge.manrique@gfpsubnacional.pe
A4: Gustavo Martin | B4: user | C4: gustavo.martin | D4: gustavo.martin.4532 | E4: Itinerante | F4: Conservación de Biodiversidad | G4: Todo el ámbito del Programa | H4: D1, CB | I4: Gestión de las Finanzas Públicas | K4: gustavo.martin@gfpsubnacional.pe
A5: Luz Garrido | B5: user | C5: lgarrido | D5: lgarrido6715 | E5: Itinerante | F5: Contrataciones | G5: Todo el ámbito del Programa | H5: R1 | I5: Gestión de las Finanzas Públicas | J5: 986723737 / 997025160 | K5: lgarrido@gfpsubnacional.pe | L5: lmgarridop@hotmail.com
A6: Eduardo Padilla | B6: user | C6: rodolfo.padilla | D6: rodolfo.padilla3100 | E6: Itinerante | F6: Inversiones | G6: Todo el ámbito del Programa | H6: R2 | I6: Gestión de las Finanzas Públicas | J6: 980449097 | K6: rodolfo.padilla@gfpsubnacional.pe | L6: eduardopadillac@hotmail.com
A7: Luis Liñán | B7: user | C7: luis.linan | D7: luis.linan8464 | E7: Itinerante | F7: Rentas | G7: Todo el ámbito del Programa | H7: R3 | I7: Gestión de las Finanzas Públicas | J7: 922756652 | K7: luis.linan@gfpsubnacional.pe | L7: eduardo_lb_2004@hotmail.com
A8: Aldo Bautista | B8: user | C8: aldo.bautista | D8: aldo.bautista5368 | E8: Itinerante | F8: Integridad y Riesgos | G8: Todo el ámbito del Programa | H8: R4 | I8: Integridad Pública | J8: 954693246 | K8: aldo.bautista@gfpsubnacional.pe
A9: Verónica Ferreyra | B9: user | C9: veronica.ferreyra | D9: veronica.ferreyra3140 | E9: Consultora | F9: Recuperación de activos | G9: Fiscalía y Poder Judicial | H9: R5 | I9: Recuperación de Activos | K9: veronica.ferreyra@gfpsubnacional.pe
A10: Sergio Jimenez | B10: user | C10: sergio.jimenez | D10: sergio.jimenez9375 | E10: Itinerante | H10: R5 | K10: sergio.jimenez@baselgovernance.org
A11: Limberg Chero | B11: user | C11: lchero | D11: lchero6776 | E11: Itinerante | F11: Coordinación institucional | G11: Todo el ámbito del Programa | H11: D1.4 | I11: Coordinación Institucional | K11: lchero@gfpsubnacional.pe
A12: Jorge Rodas | B12: user | C12: jorge.rodas | D12: jorge.rodas8451 | E12: Itinerante | F12: Publicaciones | G12: Todo el ámbito del Programa | H12: D1.6 | I12: Gestión del Conocimiento | K12: jorge.rodas@gfpsubnacional.pe
A13: Yois Avila | B13: user | C13: yois.avila | D13: yois.avila4984 | E13: Residente | F13: Rentas | G13: MPP | H13: R3 | I13: Gestión de las Finanzas Públicas | J13: 940 530 377 | K13: yois.avila@gfpsubnacional.pe
A14: Nelson Baez | B14: user | C14: nelson.baez | D14: nelson.baez2073 | E14: Residente | F14: Inversiones | G14: GORE Cusco/MP Cusco | H14: R2 | I14: Gestión de las Finanzas Públicas | J14: 980636629 | K14: nelson.baez@gfpsubnacional.pe | L14: nelsonbaezpacheco@hotmail.com
A15: Carla Berrios | B15: user | C15: carla.berrios | D15: carla.berrios6713 | E15: Residente | F15: Inversiones | G15: GORE Apurímac/MP Abancay | H15: R2 | I15: Gestión de las Finanzas Públicas | J15: 953911888 | K15: carla.berrios@gfpsubnacional.pe | L15: caberrios@gmail.com
A16: Constante Castillo | B16: user | C16: constante.castillo | D16: constante.castillo1331 | E16: Residente | F16: Inversiones | G16: GORE La Libertad/MP de Trujillo | H16: R2 | I16: Gestión de las Finanzas Públicas | J16: 949910756 | K16: constante.castillo@gfpsubnacional.pe | L16: castilloalva@gmail.com
A17: Diana Castro | B17: user | C17: diana.castro | D17: diana.castro5478 | E17: Residente | F17: Inversiones | G17: GORE Piura | H17: R2 | I17: Gestión de las Finanzas Públicas | J17: 965195777 | K17: diana.castro@gfpsubnacional.pe | L17: diancas_08@hotmail.com
A18: Xiomara Carbajal | B18: user | C18: xcarbajal | D18: xcarbajal8653 | E18: Residente | F18: Contrataciones | G18: GORE Apurímac/MP Abancay | H18: R1 | I18: Gestión de las Finanzas Públicas | J18: 989244539 | K18: xcarbajal@gfpsubnacional.pe | L18: xiomy_pezo@hotmail.com
A19: Martín Cayo | B19: user | C19: martin.cayo | D19: martin.cayo6025 | E19: Residente | F19: Contrataciones | G19: GORE Cusco/MP Cusco | H19: R1 | I19: Gestión de las Finanzas Públicas | K19: martin.cayo@gfpsubnacional.pe
A20: Delia Contreras | B20: user | C20: delia.contreras | D20: delia.contreras4759 | E20: Residente | F20: Rentas | G20: MPA, MPC | H20: R3 | I20: Gestión de las Finanzas Públicas | K20: delia.contreras@gfpsubnacional.pe
A21: Elva Cruz | B21: user | C21: elva.cruz | D21: elva.cruz6246 | E21: Residente | F21: Inversiones | G21: GORE San Martín/MP San Martin | H21: R2 | I21: Gestión de las Finanzas Públicas | J21: 945047558 | K21: elva.cruz@gfpsubnacional.pe | L21: ecruz281@hotmail.com
A22: Milagrito Diaz | B22: user | C22: milagrito.diaz | D22: milagrito.diaz9265 | E22: Residente | F22: Contrataciones | G22: GORE La Libertad/MP de Trujillo | H22: R1 | I22: Gestión de las Finanzas Públicas | J22: 914819913 | K22: milagrito.diaz@gfpsubnacional.pe | L22: mdiaz2810@yahoo.es
A23: Dalila Diaz | B23: user | C23: dalila.diaz | D23: dalila.diaz1190 | E23: Residente | F23: Contrataciones | G23: GORE San Martín/MP San Martin | H23: R1 | I23: Gestión de las Finanzas Públicas | J23: 952689761 | K23: dalila.diaz@gfpsubnacional.pe | L23: diazurcia@gmail.com
A24: Michael Ludeña | B24: user | C24: luis.ludena | D24: luis.ludena2617 | E24: Residente | F24: Rentas | G24: MPSM | H24: R3 | I24: Gestión de las Finanzas Públicas | J24: 949411116 | K24: luis.ludena@gfpsubnacional.pe
A25: Julio Morales | B25: user | C25: julio.morales | D25: julio.morales2846 | E25: Residente | F25: Inversiones | G25: GORE Lambayeque | H25: R2 | I25: Gestión de las Finanzas Públicas | K25: julio.morales@gfpsubnacional.pe
A26: Lisseth Galiano | B26: user | C26: lisseth.galiano | D26: lisseth.galiano6607 | E26: Itinerante | F26: Integridad y Riesgos | G26: Todo el ámbito del Programa | H26: R4 | I26: Integridad Pública | K26: lisseth.galiano@gfpsubnacional.pe
A27: Jorge Rojas | B27: user | C27: jrojas | D27: jrojas1529 | E27: Residente | F27: Contrataciones | G27: GORE Lambayeque | H27: R1 | I27: Gestión de las Finanzas Públicas | J27: 981800598 | K27: jrojas@gfpsubnacional.pe | L27: jorchst@gmail.com
A28: Lady Seminario | B28: user | C28: lseminario | D28: lseminario8059 | E28: Residente | F28: Contrataciones | G28: GORE Piura | H28: R1 | I28: Gestión de las Finanzas Públicas | J28: 986723762 / 975459691 | K28: lseminario@gfpsubnacional.pe | L28: semibeni@hotmail.com
A29: Luis Yzquierdo | B29: user | C29: luis.yzquierdo | D29: luis.yzquierdo1647 | E29: Residente | F29: Rentas | G29: MPT | H29: R3 | I29: Gestión de las Finanzas Públicas | K29: luis.yzquierdo@gfpsubnacional.pe
A30: Eduardo Morales | B30: user | C30: eduardo.morales | D30: eduardo.morales6128 | E30: Residente | F30: Conservación de Biodiversidad | G30: GORE Loreto | H30: CB | I30: Gestión de las Finanzas Públicas | K30: eduardo.morales@gfpsubnacional.pe
A31: Felipe Lopez | B31: user | C31: felipe.lopez | D31: felipe.lopez2025 | E31: Residente | F31: Conservación de Biodiversidad | G31: GORE Loreto | H31: CB | I31: Gestión de las Finanzas Públicas | K31: felipe.lopez@gfpsubnacional.pe
A32: Mariana León | B32: user | C32: mariana.leon | D32: mariana.leon5123 | E32: Residente | F32: Conservación de Biodiversidad | G32: GORE San Martín | H32: CB | I32: Gestión de las Finanzas Públicas | K32: mariana.leon@gfpsubnacional.pe
A33: Estrella Medina | B33: user | C33: estrella.medina | D33: estrella.medina2277 | E33: Residente | F33: Conservación de Biodiversidad | G33: GORE San Martín | H33: CB | I33: Gestión de las Finanzas Públicas | K33: estrella.medina@gfpsubnacional.pe
A34: Judith Hernández | B34: user | C34: judith.hernandez | D34: judith.hernandez7103 | E34: Residente | F34: Conservación de Biodiversidad | G34: GORE Cusco | H34: CB | I34: Gestión de las Finanzas Públicas | K34: judith.hernandez@gfpsubnacional.pe
A35: Luis Gallegos | B35: user | C35: luis.gallegos | D35: luis.gallegos9041 | E35: Residente | F35: Conservación de Biodiversidad | G35: GORE Cusco | H35: CB | I35: Gestión de las Finanzas Públicas | K35: luis.gallegos@gfpsubnacional.pe
A36: Usuario de Prueba | B36: user | C36: prueba | D36: prueba | E36: Itinerante | F36: Rentas | G36: Todo el ámbito del Programa | H36: R3 | I36: Gestión de las Finanzas Públicas | J36: 922756652 | K36: prueba@gfpsubnacional.pe | L36: prueba@hotmail.com

Sheet varios
A1: nombre | B1: opcion1 | C1: opcion2 | D1: opcion3 | E1: opcion4 | F1: opcion5 | G1: opcion6 | H1: opcion7 | I1: opcion8 | J1: opcion9 | K1: opcion10 | L1: opcion11 | M1: opcion12 | N1: opcion13 | O1: opcion14 | P1: opcion15 | Q1: opcion16 | R1: opcion17 | S1: opcion18 | T1: opcion19 | U1: opcion20 | V1: opcion21 | W1: opcion22 | X1: opcion23 | Y1: opcion24 | Z1: opcion25 | AA1: opcion26 | AB1: opcion27 | AC1: opcion28 | AD1: opcion29 | AE1: opcion30 | AF1: opcion31
A2: etapa | B2: Meta concluída | C2: Meta en proceso
A3: ambitos | B3: Ninguna | C3: Nacional | D3: Todas las regiones | E3: Todas las provincias | F3: Región Apurímac | G3: Región Cusco | H3: Región Lambayeque | I3: Región La Libertad | J3: Región Loreto | K3: Región Piura | L3: Región San Martin | M3: Provincia Abancay | N3: Provincia Cusco | O3: Provincia Maynas | P3: Provincia Trujillo | Q3: Provincia Piura | R3: Provincia San Martin
A4: entidades | B4: Ninguna | C4: Todos los GL | D4: Todos los GR | E4: Todos los GSN | F4: GRA | G4: GRC | H4: GRL | I4: GRLL | J4: GRLO | K4: GRP | L4: GRSM | M4: MPA | N4: MPC | O4: MPM | P4: MPT | Q4: MPP | R4: MPSM | S4: Fiscalía | T4: Poder Judicial | U4: Procuraduría General del Estado | V4: Presidencia del Consejo de Ministros | W4: Contraloría General de la República | X4: Ministerio de Economía y Finanzas | Y4: Ministerio de Vivienda | Z4: Ministerio de Salud | AA4: Ministerio de Educación | AB4: ENAP | AC4: SERFOR | AD4: SERNANP | AE4: OSINFOR
A5: masdeunconsultor | B5: Sí. Declaro que este es el único registro de la meta. | C5: No
A6: sino | B6: Sí | C6: No
A7: estado | B7: Concluída | C7: En proceso
